{
  "schema": {
    "name": "mundodolphins.hugo.sectioned-page",
    "version": "1.0.0"
  },
  "generated_at": "2026-02-18T11:41:06Z",
  "page": {
    "kind": "game",
    "title": "Miami Dolphins vs San Francisco 49ers",
    "date": "1992-12-06",
    "slug": "mia-san-19921206",
    "path": "historia/partidos/mia-san-19921206",
    "params": {
      "game_id": "199212060sfo"
    }
  },
  "sections": {
    "Anotaciones": {
      "linescore": [
        {
          "Equipo": "Miami Dolphins",
          "1": "0",
          "2": "0",
          "3": "3",
          "4": "0",
          "Final": "3"
        },
        {
          "Equipo": "San Francisco 49ers",
          "1": "0",
          "2": "13",
          "3": "7",
          "4": "7",
          "Final": "27"
        }
      ],
      "scoring_summary": [
        {
          "Cuarto": "2",
          "Equipo": "San Francisco 49ers",
          "Descripción": "Tom Rathman pase de 27 yardas de Steve Young",
          "Marcador visitante": "0",
          "Marcador local": "6"
        },
        {
          "Cuarto": "2",
          "Equipo": "San Francisco 49ers",
          "Descripción": "Tom Rathman carrera de 1 yarda (Mike Cofer kick)",
          "Marcador visitante": "0",
          "Marcador local": "13"
        },
        {
          "Cuarto": "3",
          "Equipo": "Miami Dolphins",
          "Descripción": "Pete Stoyanovich field goal de 32 yardas",
          "Marcador visitante": "3",
          "Marcador local": "13"
        },
        {
          "Cuarto": "3",
          "Equipo": "San Francisco 49ers",
          "Descripción": "Amp Lee carrera de 1 yarda (Mike Cofer kick)",
          "Marcador visitante": "3",
          "Marcador local": "20"
        },
        {
          "Cuarto": "4",
          "Equipo": "San Francisco 49ers",
          "Descripción": "Jerry Rice pase de 12 yardas de Steve Young (Mike Cofer kick)",
          "Marcador visitante": "3",
          "Marcador local": "27"
        }
      ]
    },
    "Conteo de snaps": {},
    "Equipos": {
      "Miami Dolphins": {
        "Coach": "Don Shula",
        "Estadísticas": {
          "Acarreos-yardas-TD": "15-40-0",
          "Capturas-yardas perdidas": "1-7",
          "Comp-Int-Yds-TD-INT": "20-36-206-0-0",
          "Conv. en cuarto down": "0-1",
          "Conv. en tercer down": "4-12",
          "Fumbles-perdidos": "2-1",
          "Penalizaciones-yardas": "5-25",
          "Primeros downs": "15",
          "Pérdidas de balón": "1",
          "Tiempo de posesión": "25:54",
          "Yardas netas por pase": "199",
          "Yardas totales": "239"
        },
        "Estadísticas por jugador": {
          "Defensiva": [
            {
              "INT": "1",
              "INT largo": "",
              "TD INT": "",
              "Yds INT": "",
              "FF": "",
              "FR": "",
              "TD FR": "",
              "Yds FR": "",
              "Nombre": "J.B. Brown",
              "Capturas": "",
              "Asist": "",
              "Tackles": "",
              "Solo": "",
              "Equipo": "MIA"
            }
          ],
          "Equipos especiales": [
            {
              "FGa": "",
              "FGm": "",
              "Nombre": "Reggie Roby",
              "Punts": "6",
              "Largo punt": "55",
              "Yds punt": "231",
              "Prom punt": "38.50",
              "Equipo": "MIA",
              "XPa": "",
              "XPm": ""
            },
            {
              "FGa": "1",
              "FGm": "1",
              "Nombre": "Pete Stoyanovich",
              "Punts": "",
              "Largo punt": "",
              "Yds punt": "",
              "Prom punt": "",
              "Equipo": "MIA",
              "XPa": "",
              "XPm": ""
            },
            {
              "Retornos KO": "2",
              "Largo retorno KO": "",
              "TD KO": "",
              "Yds KO": "42",
              "Prom KO": "21",
              "Nombre": "Bernie Parmalee",
              "Retornos punt": "",
              "Largo retorno punt": "",
              "TD punt": "",
              "Yds punt": "",
              "Prom punt": "",
              "Equipo": "MIA"
            },
            {
              "Retornos KO": "2",
              "Largo retorno KO": "",
              "TD KO": "",
              "Yds KO": "34",
              "Prom KO": "17",
              "Nombre": "Mike Williams",
              "Retornos punt": "",
              "Largo retorno punt": "",
              "TD punt": "",
              "Yds punt": "",
              "Prom punt": "",
              "Equipo": "MIA"
            }
          ],
          "Ofensiva": [
            {
              "Fumbles": "",
              "Fumbles perdidos": "",
              "Intentos": "31",
              "Comp": "19",
              "INT": "",
              "Largo pase": "24",
              "Rating": "79",
              "Capturas recibidas": "1",
              "Yds perdidas capturas": "7",
              "TD pase": "",
              "Yds pase": "192",
              "Nombre": "Dan Marino",
              "Rec": "",
              "Largo recepción": "",
              "TD recepción": "",
              "Yds recepción": "",
              "Acarreos": "",
              "Largo carrera": "",
              "TD carrera": "",
              "Yds carrera": "",
              "Objetivos": "",
              "Equipo": "MIA"
            },
            {
              "Fumbles": "",
              "Fumbles perdidos": "",
              "Intentos": "5",
              "Comp": "1",
              "INT": "",
              "Largo pase": "14",
              "Rating": "39.60",
              "Capturas recibidas": "",
              "Yds perdidas capturas": "",
              "TD pase": "",
              "Yds pase": "14",
              "Nombre": "Scott Mitchell",
              "Rec": "",
              "Largo recepción": "",
              "TD recepción": "",
              "Yds recepción": "",
              "Acarreos": "1",
              "Largo carrera": "8",
              "TD carrera": "",
              "Yds carrera": "8",
              "Objetivos": "",
              "Equipo": "MIA"
            },
            {
              "Fumbles": "",
              "Fumbles perdidos": "",
              "Intentos": "",
              "Comp": "",
              "INT": "",
              "Largo pase": "",
              "Rating": "",
              "Capturas recibidas": "",
              "Yds perdidas capturas": "",
              "TD pase": "",
              "Yds pase": "",
              "Nombre": "Tony Martin",
              "Rec": "3",
              "Largo recepción": "13",
              "TD recepción": "",
              "Yds recepción": "32",
              "Acarreos": "",
              "Largo carrera": "",
              "TD carrera": "",
              "Yds carrera": "",
              "Objetivos": "5",
              "Equipo": "MIA"
            },
            {
              "Fumbles": "",
              "Fumbles perdidos": "",
              "Intentos": "",
              "Comp": "",
              "INT": "",
              "Largo pase": "",
              "Rating": "",
              "Capturas recibidas": "",
              "Yds perdidas capturas": "",
              "TD pase": "",
              "Yds pase": "",
              "Nombre": "Bobby Humphrey",
              "Rec": "4",
              "Largo recepción": "13",
              "TD recepción": "",
              "Yds recepción": "42",
              "Acarreos": "8",
              "Largo carrera": "11",
              "TD carrera": "",
              "Yds carrera": "21",
              "Objetivos": "7",
              "Equipo": "MIA"
            },
            {
              "Fumbles": "",
              "Fumbles perdidos": "",
              "Intentos": "",
              "Comp": "",
              "INT": "",
              "Largo pase": "",
              "Rating": "",
              "Capturas recibidas": "",
              "Yds perdidas capturas": "",
              "TD pase": "",
              "Yds pase": "",
              "Nombre": "Mark Higgs",
              "Rec": "",
              "Largo recepción": "",
              "TD recepción": "",
              "Yds recepción": "",
              "Acarreos": "6",
              "Largo carrera": "6",
              "TD carrera": "",
              "Yds carrera": "11",
              "Objetivos": "1",
              "Equipo": "MIA"
            },
            {
              "Fumbles": "1",
              "Fumbles perdidos": "",
              "Intentos": "",
              "Comp": "",
              "INT": "",
              "Largo pase": "",
              "Rating": "",
              "Capturas recibidas": "",
              "Yds perdidas capturas": "",
              "TD pase": "",
              "Yds pase": "",
              "Nombre": "Keith Jackson",
              "Rec": "7",
              "Largo recepción": "20",
              "TD recepción": "",
              "Yds recepción": "63",
              "Acarreos": "",
              "Largo carrera": "",
              "TD carrera": "",
              "Yds carrera": "",
              "Objetivos": "10",
              "Equipo": "MIA"
            },
            {
              "Fumbles": "",
              "Fumbles perdidos": "",
              "Intentos": "",
              "Comp": "",
              "INT": "",
              "Largo pase": "",
              "Rating": "",
              "Capturas recibidas": "",
              "Yds perdidas capturas": "",
              "TD pase": "",
              "Yds pase": "",
              "Nombre": "Mark Duper",
              "Rec": "2",
              "Largo recepción": "23",
              "TD recepción": "",
              "Yds recepción": "39",
              "Acarreos": "",
              "Largo carrera": "",
              "TD carrera": "",
              "Yds carrera": "",
              "Objetivos": "2",
              "Equipo": "MIA"
            },
            {
              "Fumbles": "",
              "Fumbles perdidos": "",
              "Intentos": "",
              "Comp": "",
              "INT": "",
              "Largo pase": "",
              "Rating": "",
              "Capturas recibidas": "",
              "Yds perdidas capturas": "",
              "TD pase": "",
              "Yds pase": "",
              "Nombre": "James Saxon",
              "Rec": "1",
              "Largo recepción": "14",
              "TD recepción": "",
              "Yds recepción": "14",
              "Acarreos": "",
              "Largo carrera": "",
              "TD carrera": "",
              "Yds carrera": "",
              "Objetivos": "2",
              "Equipo": "MIA"
            },
            {
              "Fumbles": "",
              "Fumbles perdidos": "",
              "Intentos": "",
              "Comp": "",
              "INT": "",
              "Largo pase": "",
              "Rating": "",
              "Capturas recibidas": "",
              "Yds perdidas capturas": "",
              "TD pase": "",
              "Yds pase": "",
              "Nombre": "Mark Clayton",
              "Rec": "1",
              "Largo recepción": "8",
              "TD recepción": "",
              "Yds recepción": "8",
              "Acarreos": "",
              "Largo carrera": "",
              "TD carrera": "",
              "Yds carrera": "",
              "Objetivos": "4",
              "Equipo": "MIA"
            },
            {
              "Fumbles": "",
              "Fumbles perdidos": "",
              "Intentos": "",
              "Comp": "",
              "INT": "",
              "Largo pase": "",
              "Rating": "",
              "Capturas recibidas": "",
              "Yds perdidas capturas": "",
              "TD pase": "",
              "Yds pase": "",
              "Nombre": "Tony Paige",
              "Rec": "2",
              "Largo recepción": "5",
              "TD recepción": "",
              "Yds recepción": "8",
              "Acarreos": "",
              "Largo carrera": "",
              "TD carrera": "",
              "Yds carrera": "",
              "Objetivos": "3",
              "Equipo": "MIA"
            },
            {
              "Fumbles": "",
              "Fumbles perdidos": "",
              "Intentos": "",
              "Comp": "",
              "INT": "",
              "Largo pase": "",
              "Rating": "",
              "Capturas recibidas": "",
              "Yds perdidas capturas": "",
              "TD pase": "",
              "Yds pase": "",
              "Nombre": "Fred Banks",
              "Rec": "",
              "Largo recepción": "",
              "TD recepción": "",
              "Yds recepción": "",
              "Acarreos": "",
              "Largo carrera": "",
              "TD carrera": "",
              "Yds carrera": "",
              "Objetivos": "2",
              "Equipo": "MIA"
            }
          ]
        },
        "Puntos": 3,
        "Record": "8-5"
      },
      "San Francisco 49ers": {
        "Coach": "George Seifert",
        "Estadísticas": {
          "Acarreos-yardas-TD": "34-136-2",
          "Capturas-yardas perdidas": "0-0",
          "Comp-Int-Yds-TD-INT": "19-28-220-2-1",
          "Conv. en cuarto down": "2-2",
          "Conv. en tercer down": "7-13",
          "Fumbles-perdidos": "0-0",
          "Penalizaciones-yardas": "7-55",
          "Primeros downs": "20",
          "Pérdidas de balón": "1",
          "Tiempo de posesión": "34:06",
          "Yardas netas por pase": "220",
          "Yardas totales": "356"
        },
        "Estadísticas por jugador": {
          "Defensiva": [
            {
              "INT": "",
              "INT largo": "",
              "TD INT": "",
              "Yds INT": "",
              "FF": "",
              "FR": "",
              "TD FR": "",
              "Yds FR": "",
              "Nombre": "Tim Harris",
              "Capturas": "1",
              "Asist": "",
              "Tackles": "",
              "Solo": "",
              "Equipo": "SFO"
            },
            {
              "INT": "",
              "INT largo": "",
              "TD INT": "",
              "Yds INT": "",
              "FF": "1",
              "FR": "",
              "TD FR": "",
              "Yds FR": "",
              "Nombre": "Thane Gash",
              "Capturas": "",
              "Asist": "",
              "Tackles": "",
              "Solo": "",
              "Equipo": "SFO"
            },
            {
              "INT": "",
              "INT largo": "",
              "TD INT": "",
              "Yds INT": "",
              "FF": "",
              "FR": "1",
              "TD FR": "",
              "Yds FR": "",
              "Nombre": "Dana Hall",
              "Capturas": "",
              "Asist": "",
              "Tackles": "",
              "Solo": "",
              "Equipo": "SFO"
            },
            {
              "INT": "",
              "INT largo": "",
              "TD INT": "",
              "Yds INT": "",
              "FF": "1",
              "FR": "",
              "TD FR": "",
              "Yds FR": "",
              "Nombre": "Mike Walter",
              "Capturas": "",
              "Asist": "",
              "Tackles": "",
              "Solo": "",
              "Equipo": "SFO"
            }
          ],
          "Equipos especiales": [
            {
              "FGa": "1",
              "FGm": "",
              "Nombre": "Mike Cofer",
              "Punts": "",
              "Largo punt": "",
              "Yds punt": "",
              "Prom punt": "",
              "Equipo": "SFO",
              "XPa": "4",
              "XPm": "3"
            },
            {
              "FGa": "",
              "FGm": "",
              "Nombre": "Klaus Wilmsmeyer",
              "Punts": "2",
              "Largo punt": "27",
              "Yds punt": "54",
              "Prom punt": "27",
              "Equipo": "SFO",
              "XPa": "",
              "XPm": ""
            },
            {
              "Retornos KO": "",
              "Largo retorno KO": "",
              "TD KO": "",
              "Yds KO": "",
              "Prom KO": "",
              "Nombre": "Alan Grant",
              "Retornos punt": "1",
              "Largo retorno punt": "",
              "TD punt": "",
              "Yds punt": "",
              "Prom punt": "",
              "Equipo": "SFO"
            },
            {
              "Retornos KO": "2",
              "Largo retorno KO": "",
              "TD KO": "",
              "Yds KO": "110",
              "Prom KO": "55",
              "Nombre": "Marc Logan",
              "Retornos punt": "",
              "Largo retorno punt": "",
              "TD punt": "",
              "Yds punt": "",
              "Prom punt": "",
              "Equipo": "SFO"
            }
          ],
          "Ofensiva": [
            {
              "Fumbles": "",
              "Fumbles perdidos": "",
              "Intentos": "27",
              "Comp": "19",
              "INT": "1",
              "Largo pase": "32",
              "Rating": "103.90",
              "Capturas recibidas": "",
              "Yds perdidas capturas": "",
              "TD pase": "2",
              "Yds pase": "220",
              "Nombre": "Steve Young",
              "Rec": "",
              "Largo recepción": "",
              "TD recepción": "",
              "Yds recepción": "",
              "Acarreos": "4",
              "Largo carrera": "12",
              "TD carrera": "",
              "Yds carrera": "20",
              "Objetivos": "",
              "Equipo": "SFO"
            },
            {
              "Fumbles": "",
              "Fumbles perdidos": "",
              "Intentos": "1",
              "Comp": "",
              "INT": "",
              "Largo pase": "",
              "Rating": "39.60",
              "Capturas recibidas": "",
              "Yds perdidas capturas": "",
              "TD pase": "",
              "Yds pase": "",
              "Nombre": "Steve Bono",
              "Rec": "",
              "Largo recepción": "",
              "TD recepción": "",
              "Yds recepción": "",
              "Acarreos": "2",
              "Largo carrera": "19",
              "TD carrera": "",
              "Yds carrera": "18",
              "Objetivos": "",
              "Equipo": "SFO"
            },
            {
              "Fumbles": "",
              "Fumbles perdidos": "",
              "Intentos": "",
              "Comp": "",
              "INT": "",
              "Largo pase": "",
              "Rating": "",
              "Capturas recibidas": "",
              "Yds perdidas capturas": "",
              "TD pase": "",
              "Yds pase": "",
              "Nombre": "Amp Lee",
              "Rec": "4",
              "Largo recepción": "7",
              "TD recepción": "",
              "Yds recepción": "22",
              "Acarreos": "16",
              "Largo carrera": "9",
              "TD carrera": "1",
              "Yds carrera": "58",
              "Objetivos": "5",
              "Equipo": "SFO"
            },
            {
              "Fumbles": "",
              "Fumbles perdidos": "",
              "Intentos": "",
              "Comp": "",
              "INT": "",
              "Largo pase": "",
              "Rating": "",
              "Capturas recibidas": "",
              "Yds perdidas capturas": "",
              "TD pase": "",
              "Yds pase": "",
              "Nombre": "Tom Rathman",
              "Rec": "1",
              "Largo recepción": "27",
              "TD recepción": "1",
              "Yds recepción": "27",
              "Acarreos": "5",
              "Largo carrera": "4",
              "TD carrera": "1",
              "Yds carrera": "14",
              "Objetivos": "1",
              "Equipo": "SFO"
            },
            {
              "Fumbles": "",
              "Fumbles perdidos": "",
              "Intentos": "",
              "Comp": "",
              "INT": "",
              "Largo pase": "",
              "Rating": "",
              "Capturas recibidas": "",
              "Yds perdidas capturas": "",
              "TD pase": "",
              "Yds pase": "",
              "Nombre": "Jerry Rice",
              "Rec": "7",
              "Largo recepción": "32",
              "TD recepción": "1",
              "Yds recepción": "79",
              "Acarreos": "1",
              "Largo carrera": "10",
              "TD carrera": "",
              "Yds carrera": "10",
              "Objetivos": "9",
              "Equipo": "SFO"
            },
            {
              "Fumbles": "",
              "Fumbles perdidos": "",
              "Intentos": "",
              "Comp": "",
              "INT": "",
              "Largo pase": "",
              "Rating": "",
              "Capturas recibidas": "",
              "Yds perdidas capturas": "",
              "TD pase": "",
              "Yds pase": "",
              "Nombre": "Dexter Carter",
              "Rec": "",
              "Largo recepción": "",
              "TD recepción": "",
              "Yds recepción": "",
              "Acarreos": "4",
              "Largo carrera": "6",
              "TD carrera": "",
              "Yds carrera": "9",
              "Objetivos": "",
              "Equipo": "SFO"
            },
            {
              "Fumbles": "",
              "Fumbles perdidos": "",
              "Intentos": "",
              "Comp": "",
              "INT": "",
              "Largo pase": "",
              "Rating": "",
              "Capturas recibidas": "",
              "Yds perdidas capturas": "",
              "TD pase": "",
              "Yds pase": "",
              "Nombre": "Marc Logan",
              "Rec": "",
              "Largo recepción": "",
              "TD recepción": "",
              "Yds recepción": "",
              "Acarreos": "2",
              "Largo carrera": "4",
              "TD carrera": "",
              "Yds carrera": "7",
              "Objetivos": "",
              "Equipo": "SFO"
            },
            {
              "Fumbles": "",
              "Fumbles perdidos": "",
              "Intentos": "",
              "Comp": "",
              "INT": "",
              "Largo pase": "",
              "Rating": "",
              "Capturas recibidas": "",
              "Yds perdidas capturas": "",
              "TD pase": "",
              "Yds pase": "",
              "Nombre": "John Taylor",
              "Rec": "2",
              "Largo recepción": "20",
              "TD recepción": "",
              "Yds recepción": "32",
              "Acarreos": "",
              "Largo carrera": "",
              "TD carrera": "",
              "Yds carrera": "",
              "Objetivos": "4",
              "Equipo": "SFO"
            },
            {
              "Fumbles": "",
              "Fumbles perdidos": "",
              "Intentos": "",
              "Comp": "",
              "INT": "",
              "Largo pase": "",
              "Rating": "",
              "Capturas recibidas": "",
              "Yds perdidas capturas": "",
              "TD pase": "",
              "Yds pase": "",
              "Nombre": "Brent Jones",
              "Rec": "2",
              "Largo recepción": "24",
              "TD recepción": "",
              "Yds recepción": "26",
              "Acarreos": "",
              "Largo carrera": "",
              "TD carrera": "",
              "Yds carrera": "",
              "Objetivos": "3",
              "Equipo": "SFO"
            },
            {
              "Fumbles": "",
              "Fumbles perdidos": "",
              "Intentos": "",
              "Comp": "",
              "INT": "",
              "Largo pase": "",
              "Rating": "",
              "Capturas recibidas": "",
              "Yds perdidas capturas": "",
              "TD pase": "",
              "Yds pase": "",
              "Nombre": "Mike Sherrard",
              "Rec": "2",
              "Largo recepción": "15",
              "TD recepción": "",
              "Yds recepción": "25",
              "Acarreos": "",
              "Largo carrera": "",
              "TD carrera": "",
              "Yds carrera": "",
              "Objetivos": "2",
              "Equipo": "SFO"
            },
            {
              "Fumbles": "",
              "Fumbles perdidos": "",
              "Intentos": "",
              "Comp": "",
              "INT": "",
              "Largo pase": "",
              "Rating": "",
              "Capturas recibidas": "",
              "Yds perdidas capturas": "",
              "TD pase": "",
              "Yds pase": "",
              "Nombre": "Jamie Williams",
              "Rec": "1",
              "Largo recepción": "9",
              "TD recepción": "",
              "Yds recepción": "9",
              "Acarreos": "",
              "Largo carrera": "",
              "TD carrera": "",
              "Yds carrera": "",
              "Objetivos": "2",
              "Equipo": "SFO"
            },
            {
              "Fumbles": "",
              "Fumbles perdidos": "",
              "Intentos": "",
              "Comp": "",
              "INT": "",
              "Largo pase": "",
              "Rating": "",
              "Capturas recibidas": "",
              "Yds perdidas capturas": "",
              "TD pase": "",
              "Yds pase": "",
              "Nombre": "Odessa Turner",
              "Rec": "",
              "Largo recepción": "",
              "TD recepción": "",
              "Yds recepción": "",
              "Acarreos": "",
              "Largo carrera": "",
              "TD carrera": "",
              "Yds carrera": "",
              "Objetivos": "1",
              "Equipo": "SFO"
            }
          ]
        },
        "Puntos": 27,
        "Record": "11-2"
      }
    },
    "Estadísticas avanzadas": {
      "Puntos esperados": [
        {
          "PE Def. Pase": "-10.88",
          "PE Def. Carrera": "-8.22",
          "PE Def. Pérdidas": "0.58",
          "PE Def. Total": "-18.16",
          "PE FG/XP": "3.95",
          "PE Kicker": "2.34",
          "PE Ret. KO": "-6.51",
          "PE Of. Pase": "-8.20",
          "PE Of. Carrera": "-3.75",
          "PE Of. Pérdidas": "",
          "PE Of. Total": "-8.64",
          "PE Punter": "1.44",
          "PE Ret. Punt": "0.70",
          "PE Equipos Esp.": "1.92",
          "PE Total": "-24",
          "Equipo": "Dolphins"
        },
        {
          "PE Def. Pase": "8.20",
          "PE Def. Carrera": "3.75",
          "PE Def. Pérdidas": "",
          "PE Def. Total": "8.64",
          "PE FG/XP": "-3.95",
          "PE Kicker": "6.51",
          "PE Ret. KO": "-2.34",
          "PE Of. Pase": "10.88",
          "PE Of. Carrera": "8.22",
          "PE Of. Pérdidas": "-0.58",
          "PE Of. Total": "18.16",
          "PE Punter": "-0.70",
          "PE Ret. Punt": "-1.44",
          "PE Equipos Esp.": "-1.92",
          "PE Total": "24",
          "Equipo": "49ers"
        }
      ]
    },
    "Información del partido": {
      "Semana": "14",
      "Fecha": "6 de diciembre de 1992",
      "Estadio": "Candlestick Park",
      "Tipo de estadio": "Al aire libre",
      "Superficie de juego": "Césped",
      "Clima": "53 grados, humedad relativa 83%, viento 19 mph"
    },
    "Oficiales": [],
    "Series ofensivas": {},
    "Videos del partido": [
      {
        "youtube_id": "uaRpN6YzZXY",
        "title": "Legacy import",
        "url": "https://www.youtube.com/watch?v=uaRpN6YzZXY",
        "duration_seconds": 9840
      }
    ]
  }
}