{
  "schema": {
    "name": "mundodolphins.hugo.sectioned-page",
    "version": "1.0.0"
  },
  "generated_at": "2026-02-18T11:41:13Z",
  "page": {
    "kind": "game",
    "title": "Miami Dolphins vs Pittsburgh Steelers",
    "date": "2013-12-08",
    "slug": "mia-pit-20131208",
    "path": "historia/partidos/mia-pit-20131208",
    "params": {
      "game_id": "201312080pit"
    }
  },
  "sections": {
    "Anotaciones": {
      "linescore": [
        {
          "Equipo": "Miami Dolphins",
          "1": "3",
          "2": "7",
          "3": "14",
          "4": "10",
          "Final": "34"
        },
        {
          "Equipo": "Pittsburgh Steelers",
          "1": "7",
          "2": "0",
          "3": "14",
          "4": "7",
          "Final": "28"
        }
      ],
      "scoring_summary": [
        {
          "Cuarto": "1",
          "Tiempo": "4:20",
          "Equipo": "Pittsburgh Steelers",
          "Descripción": "Emmanuel Sanders pase de 5 yardas de Ben Roethlisberger (Shaun Suisham kick)",
          "Marcador visitante": "0",
          "Marcador local": "7"
        },
        {
          "Cuarto": "1",
          "Tiempo": "0:40",
          "Equipo": "Miami Dolphins",
          "Descripción": "Caleb Sturgis field goal de 30 yardas",
          "Marcador visitante": "3",
          "Marcador local": "7"
        },
        {
          "Cuarto": "2",
          "Tiempo": "8:15",
          "Equipo": "Miami Dolphins",
          "Descripción": "Charles Clay pase de 6 yardas de Ryan Tannehill (Caleb Sturgis kick)",
          "Marcador visitante": "10",
          "Marcador local": "7"
        },
        {
          "Cuarto": "3",
          "Tiempo": "10:50",
          "Equipo": "Miami Dolphins",
          "Descripción": "Daniel Thomas carrera de 4 yardas (Caleb Sturgis kick)",
          "Marcador visitante": "17",
          "Marcador local": "7"
        },
        {
          "Cuarto": "3",
          "Tiempo": "8:58",
          "Equipo": "Pittsburgh Steelers",
          "Descripción": "Antonio Brown pase de 43 yardas de Ben Roethlisberger (Shaun Suisham kick)",
          "Marcador visitante": "17",
          "Marcador local": "14"
        },
        {
          "Cuarto": "3",
          "Tiempo": "8:05",
          "Equipo": "Pittsburgh Steelers",
          "Descripción": "Troy Polamalu 19 yardas retorno de interception (Shaun Suisham kick)",
          "Marcador visitante": "17",
          "Marcador local": "21"
        },
        {
          "Cuarto": "3",
          "Tiempo": "4:52",
          "Equipo": "Miami Dolphins",
          "Descripción": "Brian Hartline pase de 4 yardas de Ryan Tannehill (Caleb Sturgis kick)",
          "Marcador visitante": "24",
          "Marcador local": "21"
        },
        {
          "Cuarto": "4",
          "Tiempo": "14:56",
          "Equipo": "Pittsburgh Steelers",
          "Descripción": "Jerricho Cotchery pase de 16 yardas de Ben Roethlisberger (Shaun Suisham kick)",
          "Marcador visitante": "24",
          "Marcador local": "28"
        },
        {
          "Cuarto": "4",
          "Tiempo": "2:53",
          "Equipo": "Miami Dolphins",
          "Descripción": "Charles Clay pase de 12 yardas de Ryan Tannehill (Caleb Sturgis kick)",
          "Marcador visitante": "31",
          "Marcador local": "28"
        },
        {
          "Cuarto": "4",
          "Tiempo": "1:08",
          "Equipo": "Miami Dolphins",
          "Descripción": "Caleb Sturgis field goal de 27 yardas",
          "Marcador visitante": "34",
          "Marcador local": "28"
        }
      ]
    },
    "Conteo de snaps": {
      "Miami Dolphins": [
        {
          "% defensiva": "",
          "Defensiva": "",
          "% ofensiva": "100%",
          "Ofensiva": "62",
          "Nombre": "Tyson Clabo",
          "Posición": "T",
          "Equipos especiales": "7",
          "% EE": "21%"
        },
        {
          "% defensiva": "",
          "Defensiva": "",
          "% ofensiva": "100%",
          "Ofensiva": "62",
          "Nombre": "Bryant McKinnie",
          "Posición": "T",
          "Equipos especiales": "7",
          "% EE": "21%"
        },
        {
          "% defensiva": "",
          "Defensiva": "",
          "% ofensiva": "100%",
          "Ofensiva": "62",
          "Nombre": "John Jerry",
          "Posición": "G",
          "Equipos especiales": "7",
          "% EE": "21%"
        },
        {
          "% defensiva": "",
          "Defensiva": "",
          "% ofensiva": "100%",
          "Ofensiva": "62",
          "Nombre": "Mike Pouncey",
          "Posición": "C",
          "Equipos especiales": "",
          "% EE": ""
        },
        {
          "% defensiva": "",
          "Defensiva": "",
          "% ofensiva": "100%",
          "Ofensiva": "62",
          "Nombre": "Ryan Tannehill",
          "Posición": "QB",
          "Equipos especiales": "",
          "% EE": ""
        },
        {
          "% defensiva": "",
          "Defensiva": "",
          "% ofensiva": "97%",
          "Ofensiva": "60",
          "Nombre": "Brian Hartline",
          "Posición": "WR",
          "Equipos especiales": "",
          "% EE": ""
        },
        {
          "% defensiva": "",
          "Defensiva": "",
          "% ofensiva": "92%",
          "Ofensiva": "57",
          "Nombre": "Mike Wallace",
          "Posición": "WR",
          "Equipos especiales": "",
          "% EE": ""
        },
        {
          "% defensiva": "",
          "Defensiva": "",
          "% ofensiva": "87%",
          "Ofensiva": "54",
          "Nombre": "Charles Clay",
          "Posición": "TE",
          "Equipos especiales": "5",
          "% EE": "15%"
        },
        {
          "% defensiva": "",
          "Defensiva": "",
          "% ofensiva": "77%",
          "Ofensiva": "48",
          "Nombre": "Sam Brenner",
          "Posición": "C",
          "Equipos especiales": "8",
          "% EE": "24%"
        },
        {
          "% defensiva": "",
          "Defensiva": "",
          "% ofensiva": "68%",
          "Ofensiva": "42",
          "Nombre": "Rishard Matthews",
          "Posición": "WR",
          "Equipos especiales": "5",
          "% EE": "15%"
        },
        {
          "% defensiva": "",
          "Defensiva": "",
          "% ofensiva": "66%",
          "Ofensiva": "41",
          "Nombre": "Daniel Thomas",
          "Posición": "RB",
          "Equipos especiales": "",
          "% EE": ""
        },
        {
          "% defensiva": "",
          "Defensiva": "",
          "% ofensiva": "32%",
          "Ofensiva": "20",
          "Nombre": "Dion Sims",
          "Posición": "TE",
          "Equipos especiales": "4",
          "% EE": "12%"
        },
        {
          "% defensiva": "",
          "Defensiva": "",
          "% ofensiva": "32%",
          "Ofensiva": "20",
          "Nombre": "Lamar Miller",
          "Posición": "RB",
          "Equipos especiales": "",
          "% EE": ""
        },
        {
          "% defensiva": "",
          "Defensiva": "",
          "% ofensiva": "26%",
          "Ofensiva": "16",
          "Nombre": "Nate Garner",
          "Posición": "T",
          "Equipos especiales": "7",
          "% EE": "21%"
        },
        {
          "% defensiva": "",
          "Defensiva": "",
          "% ofensiva": "18%",
          "Ofensiva": "11",
          "Nombre": "Michael Egnew",
          "Posición": "TE",
          "Equipos especiales": "1",
          "% EE": "3%"
        },
        {
          "% defensiva": "",
          "Defensiva": "",
          "% ofensiva": "3%",
          "Ofensiva": "2",
          "Nombre": "Marlon Moore",
          "Posición": "WR",
          "Equipos especiales": "18",
          "% EE": "53%"
        },
        {
          "% defensiva": "",
          "Defensiva": "",
          "% ofensiva": "2%",
          "Ofensiva": "1",
          "Nombre": "Marcus Thigpen",
          "Posición": "RB",
          "Equipos especiales": "11",
          "% EE": "32%"
        },
        {
          "% defensiva": "100%",
          "Defensiva": "66",
          "% ofensiva": "",
          "Ofensiva": "",
          "Nombre": "Chris Clemons",
          "Posición": "FS",
          "Equipos especiales": "9",
          "% EE": "26%"
        },
        {
          "% defensiva": "100%",
          "Defensiva": "66",
          "% ofensiva": "",
          "Ofensiva": "",
          "Nombre": "Brent Grimes",
          "Posición": "CB",
          "Equipos especiales": "5",
          "% EE": "15%"
        },
        {
          "% defensiva": "100%",
          "Defensiva": "66",
          "% ofensiva": "",
          "Ofensiva": "",
          "Nombre": "Reshad Jones",
          "Posición": "FS",
          "Equipos especiales": "5",
          "% EE": "15%"
        },
        {
          "% defensiva": "100%",
          "Defensiva": "66",
          "% ofensiva": "",
          "Ofensiva": "",
          "Nombre": "Dannell Ellerbe",
          "Posición": "LB",
          "Equipos especiales": "",
          "% EE": ""
        },
        {
          "% defensiva": "100%",
          "Defensiva": "66",
          "% ofensiva": "",
          "Ofensiva": "",
          "Nombre": "Philip Wheeler",
          "Posición": "LB",
          "Equipos especiales": "",
          "% EE": ""
        },
        {
          "% defensiva": "86%",
          "Defensiva": "57",
          "% ofensiva": "",
          "Ofensiva": "",
          "Nombre": "Jared Odrick",
          "Posición": "DT",
          "Equipos especiales": "4",
          "% EE": "12%"
        },
        {
          "% defensiva": "82%",
          "Defensiva": "54",
          "% ofensiva": "",
          "Ofensiva": "",
          "Nombre": "Nolan Carroll",
          "Posición": "CB",
          "Equipos especiales": "17",
          "% EE": "50%"
        },
        {
          "% defensiva": "82%",
          "Defensiva": "54",
          "% ofensiva": "",
          "Ofensiva": "",
          "Nombre": "Cameron Wake",
          "Posición": "DE",
          "Equipos especiales": "",
          "% EE": ""
        },
        {
          "% defensiva": "76%",
          "Defensiva": "50",
          "% ofensiva": "",
          "Ofensiva": "",
          "Nombre": "Olivier Vernon",
          "Posición": "DE",
          "Equipos especiales": "4",
          "% EE": "12%"
        },
        {
          "% defensiva": "74%",
          "Defensiva": "49",
          "% ofensiva": "",
          "Ofensiva": "",
          "Nombre": "Jimmy Wilson",
          "Posición": "FS",
          "Equipos especiales": "17",
          "% EE": "50%"
        },
        {
          "% defensiva": "64%",
          "Defensiva": "42",
          "% ofensiva": "",
          "Ofensiva": "",
          "Nombre": "Randy Starks",
          "Posición": "DT",
          "Equipos especiales": "4",
          "% EE": "12%"
        },
        {
          "% defensiva": "35%",
          "Defensiva": "23",
          "% ofensiva": "",
          "Ofensiva": "",
          "Nombre": "Dion Jordan",
          "Posición": "DE",
          "Equipos especiales": "22",
          "% EE": "65%"
        },
        {
          "% defensiva": "33%",
          "Defensiva": "22",
          "% ofensiva": "",
          "Ofensiva": "",
          "Nombre": "Koa Misi",
          "Posición": "LB",
          "Equipos especiales": "4",
          "% EE": "12%"
        },
        {
          "% defensiva": "32%",
          "Defensiva": "21",
          "% ofensiva": "",
          "Ofensiva": "",
          "Nombre": "Paul Soliai",
          "Posición": "DT",
          "Equipos especiales": "3",
          "% EE": "9%"
        },
        {
          "% defensiva": "18%",
          "Defensiva": "12",
          "% ofensiva": "",
          "Ofensiva": "",
          "Nombre": "Derrick Shelby",
          "Posición": "DE",
          "Equipos especiales": "11",
          "% EE": "32%"
        },
        {
          "% defensiva": "18%",
          "Defensiva": "12",
          "% ofensiva": "",
          "Ofensiva": "",
          "Nombre": "Dimitri Patterson",
          "Posición": "CB",
          "Equipos especiales": "",
          "% EE": ""
        },
        {
          "% defensiva": "",
          "Defensiva": "",
          "% ofensiva": "",
          "Ofensiva": "",
          "Nombre": "Jason Trusnik",
          "Posición": "LB",
          "Equipos especiales": "34",
          "% EE": "100%"
        },
        {
          "% defensiva": "",
          "Defensiva": "",
          "% ofensiva": "",
          "Ofensiva": "",
          "Nombre": "Jonathan Freeny",
          "Posición": "LB",
          "Equipos especiales": "27",
          "% EE": "79%"
        },
        {
          "% defensiva": "",
          "Defensiva": "",
          "% ofensiva": "",
          "Ofensiva": "",
          "Nombre": "Don Jones",
          "Posición": "FS",
          "Equipos especiales": "23",
          "% EE": "68%"
        },
        {
          "% defensiva": "",
          "Defensiva": "",
          "% ofensiva": "",
          "Ofensiva": "",
          "Nombre": "Austin Spitler",
          "Posición": "LB",
          "Equipos especiales": "17",
          "% EE": "50%"
        },
        {
          "% defensiva": "",
          "Defensiva": "",
          "% ofensiva": "",
          "Ofensiva": "",
          "Nombre": "Jordan Kovacs",
          "Posición": "DB",
          "Equipos especiales": "16",
          "% EE": "47%"
        },
        {
          "% defensiva": "",
          "Defensiva": "",
          "% ofensiva": "",
          "Ofensiva": "",
          "Nombre": "Caleb Sturgis",
          "Posición": "K",
          "Equipos especiales": "14",
          "% EE": "41%"
        },
        {
          "% defensiva": "",
          "Defensiva": "",
          "% ofensiva": "",
          "Ofensiva": "",
          "Nombre": "Mike Gillislee",
          "Posición": "RB",
          "Equipos especiales": "13",
          "% EE": "38%"
        },
        {
          "% defensiva": "",
          "Defensiva": "",
          "% ofensiva": "",
          "Ofensiva": "",
          "Nombre": "Jelani Jenkins",
          "Posición": "LB",
          "Equipos especiales": "12",
          "% EE": "35%"
        },
        {
          "% defensiva": "",
          "Defensiva": "",
          "% ofensiva": "",
          "Ofensiva": "",
          "Nombre": "Brandon Fields",
          "Posición": "P",
          "Equipos especiales": "12",
          "% EE": "35%"
        },
        {
          "% defensiva": "",
          "Defensiva": "",
          "% ofensiva": "",
          "Ofensiva": "",
          "Nombre": "John Denney",
          "Posición": "LS",
          "Equipos especiales": "12",
          "% EE": "35%"
        },
        {
          "% defensiva": "",
          "Defensiva": "",
          "% ofensiva": "",
          "Ofensiva": "",
          "Nombre": "Dallas Thomas",
          "Posición": "G",
          "Equipos especiales": "7",
          "% EE": "21%"
        },
        {
          "% defensiva": "",
          "Defensiva": "",
          "% ofensiva": "",
          "Ofensiva": "",
          "Nombre": "R.J. Stanford",
          "Posición": "CB",
          "Equipos especiales": "2",
          "% EE": "6%"
        }
      ],
      "Pittsburgh Steelers": [
        {
          "% defensiva": "",
          "Defensiva": "",
          "% ofensiva": "100%",
          "Ofensiva": "66",
          "Nombre": "Mike Adams",
          "Posición": "T",
          "Equipos especiales": "4",
          "% EE": "12%"
        },
        {
          "% defensiva": "",
          "Defensiva": "",
          "% ofensiva": "100%",
          "Ofensiva": "66",
          "Nombre": "Marcus Gilbert",
          "Posición": "T",
          "Equipos especiales": "4",
          "% EE": "12%"
        },
        {
          "% defensiva": "",
          "Defensiva": "",
          "% ofensiva": "100%",
          "Ofensiva": "66",
          "Nombre": "Ramon Foster",
          "Posición": "G",
          "Equipos especiales": "4",
          "% EE": "12%"
        },
        {
          "% defensiva": "",
          "Defensiva": "",
          "% ofensiva": "100%",
          "Ofensiva": "66",
          "Nombre": "David DeCastro",
          "Posición": "G",
          "Equipos especiales": "4",
          "% EE": "12%"
        },
        {
          "% defensiva": "",
          "Defensiva": "",
          "% ofensiva": "100%",
          "Ofensiva": "66",
          "Nombre": "Cody Wallace",
          "Posición": "C",
          "Equipos especiales": "",
          "% EE": ""
        },
        {
          "% defensiva": "",
          "Defensiva": "",
          "% ofensiva": "100%",
          "Ofensiva": "66",
          "Nombre": "Ben Roethlisberger",
          "Posición": "QB",
          "Equipos especiales": "",
          "% EE": ""
        },
        {
          "% defensiva": "",
          "Defensiva": "",
          "% ofensiva": "100%",
          "Ofensiva": "66",
          "Nombre": "Heath Miller",
          "Posición": "TE",
          "Equipos especiales": "",
          "% EE": ""
        },
        {
          "% defensiva": "",
          "Defensiva": "",
          "% ofensiva": "88%",
          "Ofensiva": "58",
          "Nombre": "Emmanuel Sanders",
          "Posición": "WR",
          "Equipos especiales": "6",
          "% EE": "18%"
        },
        {
          "% defensiva": "",
          "Defensiva": "",
          "% ofensiva": "88%",
          "Ofensiva": "58",
          "Nombre": "Antonio Brown",
          "Posición": "WR",
          "Equipos especiales": "5",
          "% EE": "15%"
        },
        {
          "% defensiva": "",
          "Defensiva": "",
          "% ofensiva": "83%",
          "Ofensiva": "55",
          "Nombre": "Jerricho Cotchery",
          "Posición": "WR",
          "Equipos especiales": "",
          "% EE": ""
        },
        {
          "% defensiva": "",
          "Defensiva": "",
          "% ofensiva": "83%",
          "Ofensiva": "55",
          "Nombre": "Le'Veon Bell",
          "Posición": "RB",
          "Equipos especiales": "",
          "% EE": ""
        },
        {
          "% defensiva": "",
          "Defensiva": "",
          "% ofensiva": "23%",
          "Ofensiva": "15",
          "Nombre": "Matt Spaeth",
          "Posición": "TE",
          "Equipos especiales": "",
          "% EE": ""
        },
        {
          "% defensiva": "",
          "Defensiva": "",
          "% ofensiva": "14%",
          "Ofensiva": "9",
          "Nombre": "Will Johnson",
          "Posición": "FB",
          "Equipos especiales": "19",
          "% EE": "56%"
        },
        {
          "% defensiva": "",
          "Defensiva": "",
          "% ofensiva": "11%",
          "Ofensiva": "7",
          "Nombre": "Jonathan Dwyer",
          "Posición": "RB",
          "Equipos especiales": "12",
          "% EE": "35%"
        },
        {
          "% defensiva": "",
          "Defensiva": "",
          "% ofensiva": "6%",
          "Ofensiva": "4",
          "Nombre": "Markus Wheaton",
          "Posición": "WR",
          "Equipos especiales": "16",
          "% EE": "47%"
        },
        {
          "% defensiva": "",
          "Defensiva": "",
          "% ofensiva": "3%",
          "Ofensiva": "2",
          "Nombre": "Felix Jones",
          "Posición": "RB",
          "Equipos especiales": "1",
          "% EE": "3%"
        },
        {
          "% defensiva": "",
          "Defensiva": "",
          "% ofensiva": "2%",
          "Ofensiva": "1",
          "Nombre": "Michael Palmer",
          "Posición": "TE",
          "Equipos especiales": "17",
          "% EE": "50%"
        },
        {
          "% defensiva": "100%",
          "Defensiva": "62",
          "% ofensiva": "",
          "Ofensiva": "",
          "Nombre": "Jason Worilds",
          "Posición": "LB",
          "Equipos especiales": "13",
          "% EE": "38%"
        },
        {
          "% defensiva": "100%",
          "Defensiva": "62",
          "% ofensiva": "",
          "Ofensiva": "",
          "Nombre": "Cortez Allen",
          "Posición": "CB",
          "Equipos especiales": "10",
          "% EE": "29%"
        },
        {
          "% defensiva": "100%",
          "Defensiva": "62",
          "% ofensiva": "",
          "Ofensiva": "",
          "Nombre": "Lawrence Timmons",
          "Posición": "LB",
          "Equipos especiales": "7",
          "% EE": "21%"
        },
        {
          "% defensiva": "100%",
          "Defensiva": "62",
          "% ofensiva": "",
          "Ofensiva": "",
          "Nombre": "Ryan Clark",
          "Posición": "FS",
          "Equipos especiales": "7",
          "% EE": "21%"
        },
        {
          "% defensiva": "100%",
          "Defensiva": "62",
          "% ofensiva": "",
          "Ofensiva": "",
          "Nombre": "Troy Polamalu",
          "Posición": "SS",
          "Equipos especiales": "6",
          "% EE": "18%"
        },
        {
          "% defensiva": "97%",
          "Defensiva": "60",
          "% ofensiva": "",
          "Ofensiva": "",
          "Nombre": "Ike Taylor",
          "Posición": "CB",
          "Equipos especiales": "7",
          "% EE": "21%"
        },
        {
          "% defensiva": "95%",
          "Defensiva": "59",
          "% ofensiva": "",
          "Ofensiva": "",
          "Nombre": "Cameron Heyward",
          "Posición": "DE",
          "Equipos especiales": "15",
          "% EE": "44%"
        },
        {
          "% defensiva": "74%",
          "Defensiva": "46",
          "% ofensiva": "",
          "Ofensiva": "",
          "Nombre": "William Gay",
          "Posición": "CB",
          "Equipos especiales": "7",
          "% EE": "21%"
        },
        {
          "% defensiva": "73%",
          "Defensiva": "45",
          "% ofensiva": "",
          "Ofensiva": "",
          "Nombre": "Will Allen",
          "Posición": "SS",
          "Equipos especiales": "15",
          "% EE": "44%"
        },
        {
          "% defensiva": "68%",
          "Defensiva": "42",
          "% ofensiva": "",
          "Ofensiva": "",
          "Nombre": "Evander Hood",
          "Posición": "DE",
          "Equipos especiales": "4",
          "% EE": "12%"
        },
        {
          "% defensiva": "66%",
          "Defensiva": "41",
          "% ofensiva": "",
          "Ofensiva": "",
          "Nombre": "LaMarr Woodley",
          "Posición": "LB",
          "Equipos especiales": "",
          "% EE": ""
        },
        {
          "% defensiva": "35%",
          "Defensiva": "22",
          "% ofensiva": "",
          "Ofensiva": "",
          "Nombre": "Al Woods",
          "Posición": "DE",
          "Equipos especiales": "14",
          "% EE": "41%"
        },
        {
          "% defensiva": "34%",
          "Defensiva": "21",
          "% ofensiva": "",
          "Ofensiva": "",
          "Nombre": "Jarvis Jones",
          "Posición": "LB",
          "Equipos especiales": "3",
          "% EE": "9%"
        },
        {
          "% defensiva": "27%",
          "Defensiva": "17",
          "% ofensiva": "",
          "Ofensiva": "",
          "Nombre": "Vince Williams",
          "Posición": "LB",
          "Equipos especiales": "19",
          "% EE": "56%"
        },
        {
          "% defensiva": "23%",
          "Defensiva": "14",
          "% ofensiva": "",
          "Ofensiva": "",
          "Nombre": "Steve McLendon",
          "Posición": "NT",
          "Equipos especiales": "3",
          "% EE": "9%"
        },
        {
          "% defensiva": "6%",
          "Defensiva": "4",
          "% ofensiva": "",
          "Ofensiva": "",
          "Nombre": "Hebron Fangupo",
          "Posición": "NT",
          "Equipos especiales": "7",
          "% EE": "21%"
        },
        {
          "% defensiva": "2%",
          "Defensiva": "1",
          "% ofensiva": "",
          "Ofensiva": "",
          "Nombre": "Antwon Blake",
          "Posición": "CB",
          "Equipos especiales": "23",
          "% EE": "68%"
        },
        {
          "% defensiva": "",
          "Defensiva": "",
          "% ofensiva": "",
          "Ofensiva": "",
          "Nombre": "Terence Garvin",
          "Posición": "LB",
          "Equipos especiales": "23",
          "% EE": "68%"
        },
        {
          "% defensiva": "",
          "Defensiva": "",
          "% ofensiva": "",
          "Ofensiva": "",
          "Nombre": "David Paulson",
          "Posición": "TE",
          "Equipos especiales": "17",
          "% EE": "50%"
        },
        {
          "% defensiva": "",
          "Defensiva": "",
          "% ofensiva": "",
          "Ofensiva": "",
          "Nombre": "Robert Golden",
          "Posición": "FS",
          "Equipos especiales": "16",
          "% EE": "47%"
        },
        {
          "% defensiva": "",
          "Defensiva": "",
          "% ofensiva": "",
          "Ofensiva": "",
          "Nombre": "Chris Carter",
          "Posición": "LB",
          "Equipos especiales": "14",
          "% EE": "41%"
        },
        {
          "% defensiva": "",
          "Defensiva": "",
          "% ofensiva": "",
          "Ofensiva": "",
          "Nombre": "Mat McBriar",
          "Posición": "P",
          "Equipos especiales": "10",
          "% EE": "29%"
        },
        {
          "% defensiva": "",
          "Defensiva": "",
          "% ofensiva": "",
          "Ofensiva": "",
          "Nombre": "Shamarko Thomas",
          "Posición": "SS",
          "Equipos especiales": "10",
          "% EE": "29%"
        },
        {
          "% defensiva": "",
          "Defensiva": "",
          "% ofensiva": "",
          "Ofensiva": "",
          "Nombre": "Greg Warren",
          "Posición": "LS",
          "Equipos especiales": "10",
          "% EE": "29%"
        },
        {
          "% defensiva": "",
          "Defensiva": "",
          "% ofensiva": "",
          "Ofensiva": "",
          "Nombre": "Shaun Suisham",
          "Posición": "K",
          "Equipos especiales": "9",
          "% EE": "26%"
        },
        {
          "% defensiva": "",
          "Defensiva": "",
          "% ofensiva": "",
          "Ofensiva": "",
          "Nombre": "Stevenson Sylvester",
          "Posición": "LB",
          "Equipos especiales": "9",
          "% EE": "26%"
        },
        {
          "% defensiva": "",
          "Defensiva": "",
          "% ofensiva": "",
          "Ofensiva": "",
          "Nombre": "Guy Whimper",
          "Posición": "G",
          "Equipos especiales": "4",
          "% EE": "12%"
        }
      ]
    },
    "Equipos": {
      "Miami Dolphins": {
        "Coach": "Joe Philbin",
        "Estadísticas": {
          "Acarreos-yardas-TD": "25-181-1",
          "Capturas-yardas perdidas": "2-14",
          "Comp-Int-Yds-TD-INT": "20-33-200-3-1",
          "Conv. en cuarto down": "0-0",
          "Conv. en tercer down": "6-14",
          "Fumbles-perdidos": "2-0",
          "Penalizaciones-yardas": "5-36",
          "Primeros downs": "18",
          "Pérdidas de balón": "1",
          "Tiempo de posesión": "28:55",
          "Yardas netas por pase": "186",
          "Yardas totales": "367"
        },
        "Estadísticas por jugador": {
          "Defensiva": [
            {
              "INT": "",
              "INT largo": "",
              "TD INT": "",
              "Yds INT": "",
              "FF": "",
              "FR": "1",
              "TD FR": "",
              "Yds FR": "",
              "Pases defendidos": "",
              "Nombre": "Randy Starks",
              "Golpes QB": "1",
              "Capturas": "1",
              "Asist": "",
              "Tackles": "5",
              "TFL": "1",
              "Solo": "5",
              "Equipo": "MIA"
            },
            {
              "INT": "",
              "INT largo": "",
              "TD INT": "",
              "Yds INT": "",
              "FF": "1",
              "FR": "",
              "TD FR": "",
              "Yds FR": "",
              "Pases defendidos": "",
              "Nombre": "Cameron Wake",
              "Golpes QB": "1",
              "Capturas": "1",
              "Asist": "",
              "Tackles": "3",
              "TFL": "",
              "Solo": "3",
              "Equipo": "MIA"
            },
            {
              "INT": "",
              "INT largo": "",
              "TD INT": "",
              "Yds INT": "",
              "FF": "",
              "FR": "",
              "TD FR": "",
              "Yds FR": "",
              "Pases defendidos": "",
              "Nombre": "Olivier Vernon",
              "Golpes QB": "1",
              "Capturas": "1",
              "Asist": "",
              "Tackles": "2",
              "TFL": "1",
              "Solo": "2",
              "Equipo": "MIA"
            },
            {
              "INT": "",
              "INT largo": "",
              "TD INT": "",
              "Yds INT": "",
              "FF": "",
              "FR": "",
              "TD FR": "",
              "Yds FR": "",
              "Pases defendidos": "1",
              "Nombre": "Chris Clemons",
              "Golpes QB": "",
              "Capturas": "",
              "Asist": "6",
              "Tackles": "13",
              "TFL": "",
              "Solo": "7",
              "Equipo": "MIA"
            },
            {
              "INT": "",
              "INT largo": "",
              "TD INT": "",
              "Yds INT": "",
              "FF": "",
              "FR": "",
              "TD FR": "",
              "Yds FR": "",
              "Pases defendidos": "",
              "Nombre": "Philip Wheeler",
              "Golpes QB": "",
              "Capturas": "",
              "Asist": "4",
              "Tackles": "7",
              "TFL": "",
              "Solo": "3",
              "Equipo": "MIA"
            },
            {
              "INT": "",
              "INT largo": "",
              "TD INT": "",
              "Yds INT": "",
              "FF": "",
              "FR": "",
              "TD FR": "",
              "Yds FR": "",
              "Pases defendidos": "",
              "Nombre": "Dannell Ellerbe",
              "Golpes QB": "",
              "Capturas": "",
              "Asist": "2",
              "Tackles": "5",
              "TFL": "",
              "Solo": "3",
              "Equipo": "MIA"
            },
            {
              "INT": "",
              "INT largo": "",
              "TD INT": "",
              "Yds INT": "",
              "FF": "",
              "FR": "",
              "TD FR": "",
              "Yds FR": "",
              "Pases defendidos": "1",
              "Nombre": "Reshad Jones",
              "Golpes QB": "",
              "Capturas": "",
              "Asist": "2",
              "Tackles": "5",
              "TFL": "1",
              "Solo": "3",
              "Equipo": "MIA"
            },
            {
              "INT": "",
              "INT largo": "",
              "TD INT": "",
              "Yds INT": "",
              "FF": "",
              "FR": "",
              "TD FR": "",
              "Yds FR": "",
              "Pases defendidos": "",
              "Nombre": "Jimmy Wilson",
              "Golpes QB": "",
              "Capturas": "",
              "Asist": "1",
              "Tackles": "5",
              "TFL": "",
              "Solo": "4",
              "Equipo": "MIA"
            },
            {
              "INT": "",
              "INT largo": "",
              "TD INT": "",
              "Yds INT": "",
              "FF": "",
              "FR": "",
              "TD FR": "",
              "Yds FR": "",
              "Pases defendidos": "1",
              "Nombre": "Nolan Carroll",
              "Golpes QB": "",
              "Capturas": "",
              "Asist": "2",
              "Tackles": "3",
              "TFL": "",
              "Solo": "1",
              "Equipo": "MIA"
            },
            {
              "INT": "",
              "INT largo": "",
              "TD INT": "",
              "Yds INT": "",
              "FF": "",
              "FR": "",
              "TD FR": "",
              "Yds FR": "",
              "Pases defendidos": "1",
              "Nombre": "Brent Grimes",
              "Golpes QB": "1",
              "Capturas": "",
              "Asist": "1",
              "Tackles": "3",
              "TFL": "",
              "Solo": "2",
              "Equipo": "MIA"
            },
            {
              "INT": "",
              "INT largo": "",
              "TD INT": "",
              "Yds INT": "",
              "FF": "",
              "FR": "",
              "TD FR": "",
              "Yds FR": "",
              "Pases defendidos": "",
              "Nombre": "Koa Misi",
              "Golpes QB": "",
              "Capturas": "",
              "Asist": "2",
              "Tackles": "3",
              "TFL": "",
              "Solo": "1",
              "Equipo": "MIA"
            },
            {
              "INT": "",
              "INT largo": "",
              "TD INT": "",
              "Yds INT": "",
              "FF": "",
              "FR": "",
              "TD FR": "",
              "Yds FR": "",
              "Pases defendidos": "",
              "Nombre": "Jonathan Freeny",
              "Golpes QB": "",
              "Capturas": "",
              "Asist": "1",
              "Tackles": "2",
              "TFL": "",
              "Solo": "1",
              "Equipo": "MIA"
            },
            {
              "INT": "",
              "INT largo": "",
              "TD INT": "",
              "Yds INT": "",
              "FF": "",
              "FR": "",
              "TD FR": "",
              "Yds FR": "",
              "Pases defendidos": "",
              "Nombre": "Dion Jordan",
              "Golpes QB": "",
              "Capturas": "",
              "Asist": "1",
              "Tackles": "2",
              "TFL": "",
              "Solo": "1",
              "Equipo": "MIA"
            },
            {
              "INT": "",
              "INT largo": "",
              "TD INT": "",
              "Yds INT": "",
              "FF": "",
              "FR": "",
              "TD FR": "",
              "Yds FR": "",
              "Pases defendidos": "",
              "Nombre": "Jared Odrick",
              "Golpes QB": "1",
              "Capturas": "",
              "Asist": "1",
              "Tackles": "2",
              "TFL": "",
              "Solo": "1",
              "Equipo": "MIA"
            },
            {
              "INT": "",
              "INT largo": "",
              "TD INT": "",
              "Yds INT": "",
              "FF": "",
              "FR": "",
              "TD FR": "",
              "Yds FR": "",
              "Pases defendidos": "",
              "Nombre": "Derrick Shelby",
              "Golpes QB": "",
              "Capturas": "",
              "Asist": "",
              "Tackles": "2",
              "TFL": "",
              "Solo": "2",
              "Equipo": "MIA"
            },
            {
              "INT": "",
              "INT largo": "",
              "TD INT": "",
              "Yds INT": "",
              "FF": "",
              "FR": "",
              "TD FR": "",
              "Yds FR": "",
              "Pases defendidos": "",
              "Nombre": "John Denney",
              "Golpes QB": "",
              "Capturas": "",
              "Asist": "1",
              "Tackles": "1",
              "TFL": "",
              "Solo": "",
              "Equipo": "MIA"
            },
            {
              "INT": "",
              "INT largo": "",
              "TD INT": "",
              "Yds INT": "",
              "FF": "",
              "FR": "",
              "TD FR": "",
              "Yds FR": "",
              "Pases defendidos": "",
              "Nombre": "Mike Gillislee",
              "Golpes QB": "",
              "Capturas": "",
              "Asist": "",
              "Tackles": "1",
              "TFL": "",
              "Solo": "1",
              "Equipo": "MIA"
            },
            {
              "INT": "",
              "INT largo": "",
              "TD INT": "",
              "Yds INT": "",
              "FF": "",
              "FR": "",
              "TD FR": "",
              "Yds FR": "",
              "Pases defendidos": "",
              "Nombre": "Don Jones",
              "Golpes QB": "",
              "Capturas": "",
              "Asist": "",
              "Tackles": "1",
              "TFL": "",
              "Solo": "1",
              "Equipo": "MIA"
            },
            {
              "INT": "",
              "INT largo": "",
              "TD INT": "",
              "Yds INT": "",
              "FF": "",
              "FR": "",
              "TD FR": "",
              "Yds FR": "",
              "Pases defendidos": "",
              "Nombre": "Marlon Moore",
              "Golpes QB": "",
              "Capturas": "",
              "Asist": "",
              "Tackles": "1",
              "TFL": "",
              "Solo": "1",
              "Equipo": "MIA"
            },
            {
              "INT": "",
              "INT largo": "",
              "TD INT": "",
              "Yds INT": "",
              "FF": "",
              "FR": "",
              "TD FR": "",
              "Yds FR": "",
              "Pases defendidos": "",
              "Nombre": "Dimitri Patterson",
              "Golpes QB": "",
              "Capturas": "",
              "Asist": "",
              "Tackles": "1",
              "TFL": "",
              "Solo": "1",
              "Equipo": "MIA"
            },
            {
              "INT": "",
              "INT largo": "",
              "TD INT": "",
              "Yds INT": "",
              "FF": "",
              "FR": "",
              "TD FR": "",
              "Yds FR": "",
              "Pases defendidos": "1",
              "Nombre": "Paul Soliai",
              "Golpes QB": "",
              "Capturas": "",
              "Asist": "1",
              "Tackles": "1",
              "TFL": "",
              "Solo": "",
              "Equipo": "MIA"
            },
            {
              "INT": "",
              "INT largo": "",
              "TD INT": "",
              "Yds INT": "",
              "FF": "",
              "FR": "",
              "TD FR": "",
              "Yds FR": "",
              "Pases defendidos": "",
              "Nombre": "Austin Spitler",
              "Golpes QB": "",
              "Capturas": "",
              "Asist": "",
              "Tackles": "1",
              "TFL": "",
              "Solo": "1",
              "Equipo": "MIA"
            },
            {
              "INT": "",
              "INT largo": "",
              "TD INT": "",
              "Yds INT": "",
              "FF": "",
              "FR": "",
              "TD FR": "",
              "Yds FR": "",
              "Pases defendidos": "",
              "Nombre": "Jason Trusnik",
              "Golpes QB": "",
              "Capturas": "",
              "Asist": "",
              "Tackles": "1",
              "TFL": "",
              "Solo": "1",
              "Equipo": "MIA"
            },
            {
              "INT": "",
              "INT largo": "",
              "TD INT": "",
              "Yds INT": "",
              "FF": "",
              "FR": "1",
              "TD FR": "",
              "Yds FR": "-7",
              "Pases defendidos": "",
              "Nombre": "Ryan Tannehill",
              "Golpes QB": "",
              "Capturas": "",
              "Asist": "",
              "Tackles": "",
              "TFL": "",
              "Solo": "",
              "Equipo": "MIA"
            }
          ],
          "Equipos especiales": [
            {
              "FGa": "3",
              "FGm": "2",
              "Nombre": "Caleb Sturgis",
              "Punts": "",
              "Largo punt": "",
              "Yds punt": "",
              "Prom punt": "",
              "Equipo": "MIA",
              "XPa": "4",
              "XPm": "4"
            },
            {
              "FGa": "",
              "FGm": "",
              "Nombre": "Brandon Fields",
              "Punts": "5",
              "Largo punt": "52",
              "Yds punt": "232",
              "Prom punt": "46.40",
              "Equipo": "MIA",
              "XPa": "",
              "XPm": ""
            },
            {
              "Retornos KO": "4",
              "Largo retorno KO": "25",
              "TD KO": "",
              "Yds KO": "82",
              "Prom KO": "20.50",
              "Nombre": "Marcus Thigpen",
              "Retornos punt": "2",
              "Largo retorno punt": "16",
              "TD punt": "",
              "Yds punt": "22",
              "Prom punt": "11",
              "Equipo": "MIA"
            }
          ],
          "Ofensiva": [
            {
              "Fumbles": "1",
              "Fumbles perdidos": "",
              "Intentos": "33",
              "Comp": "20",
              "INT": "1",
              "Largo pase": "40",
              "Rating": "95.50",
              "Capturas recibidas": "2",
              "Yds perdidas capturas": "14",
              "TD pase": "3",
              "Yds pase": "200",
              "Nombre": "Ryan Tannehill",
              "Rec": "",
              "Largo recepción": "",
              "TD recepción": "",
              "Yds recepción": "",
              "Acarreos": "3",
              "Largo carrera": "48",
              "TD carrera": "",
              "Yds carrera": "56",
              "Objetivos": "",
              "Equipo": "MIA"
            },
            {
              "Fumbles": "",
              "Fumbles perdidos": "",
              "Intentos": "",
              "Comp": "",
              "INT": "",
              "Largo pase": "",
              "Rating": "",
              "Capturas recibidas": "",
              "Yds perdidas capturas": "",
              "TD pase": "",
              "Yds pase": "",
              "Nombre": "Daniel Thomas",
              "Rec": "1",
              "Largo recepción": "4",
              "TD recepción": "",
              "Yds recepción": "4",
              "Acarreos": "16",
              "Largo carrera": "55",
              "TD carrera": "1",
              "Yds carrera": "105",
              "Objetivos": "1",
              "Equipo": "MIA"
            },
            {
              "Fumbles": "",
              "Fumbles perdidos": "",
              "Intentos": "",
              "Comp": "",
              "INT": "",
              "Largo pase": "",
              "Rating": "",
              "Capturas recibidas": "",
              "Yds perdidas capturas": "",
              "TD pase": "",
              "Yds pase": "",
              "Nombre": "Lamar Miller",
              "Rec": "2",
              "Largo recepción": "13",
              "TD recepción": "",
              "Yds recepción": "13",
              "Acarreos": "6",
              "Largo carrera": "7",
              "TD carrera": "",
              "Yds carrera": "20",
              "Objetivos": "4",
              "Equipo": "MIA"
            },
            {
              "Fumbles": "",
              "Fumbles perdidos": "",
              "Intentos": "",
              "Comp": "",
              "INT": "",
              "Largo pase": "",
              "Rating": "",
              "Capturas recibidas": "",
              "Yds perdidas capturas": "",
              "TD pase": "",
              "Yds pase": "",
              "Nombre": "Charles Clay",
              "Rec": "7",
              "Largo recepción": "40",
              "TD recepción": "2",
              "Yds recepción": "97",
              "Acarreos": "",
              "Largo carrera": "",
              "TD carrera": "",
              "Yds carrera": "",
              "Objetivos": "10",
              "Equipo": "MIA"
            },
            {
              "Fumbles": "",
              "Fumbles perdidos": "",
              "Intentos": "",
              "Comp": "",
              "INT": "",
              "Largo pase": "",
              "Rating": "",
              "Capturas recibidas": "",
              "Yds perdidas capturas": "",
              "TD pase": "",
              "Yds pase": "",
              "Nombre": "Brian Hartline",
              "Rec": "5",
              "Largo recepción": "18",
              "TD recepción": "1",
              "Yds recepción": "51",
              "Acarreos": "",
              "Largo carrera": "",
              "TD carrera": "",
              "Yds carrera": "",
              "Objetivos": "8",
              "Equipo": "MIA"
            },
            {
              "Fumbles": "",
              "Fumbles perdidos": "",
              "Intentos": "",
              "Comp": "",
              "INT": "",
              "Largo pase": "",
              "Rating": "",
              "Capturas recibidas": "",
              "Yds perdidas capturas": "",
              "TD pase": "",
              "Yds pase": "",
              "Nombre": "Mike Wallace",
              "Rec": "2",
              "Largo recepción": "12",
              "TD recepción": "",
              "Yds recepción": "19",
              "Acarreos": "",
              "Largo carrera": "",
              "TD carrera": "",
              "Yds carrera": "",
              "Objetivos": "5",
              "Equipo": "MIA"
            },
            {
              "Fumbles": "",
              "Fumbles perdidos": "",
              "Intentos": "",
              "Comp": "",
              "INT": "",
              "Largo pase": "",
              "Rating": "",
              "Capturas recibidas": "",
              "Yds perdidas capturas": "",
              "TD pase": "",
              "Yds pase": "",
              "Nombre": "Dion Sims",
              "Rec": "1",
              "Largo recepción": "7",
              "TD recepción": "",
              "Yds recepción": "7",
              "Acarreos": "",
              "Largo carrera": "",
              "TD carrera": "",
              "Yds carrera": "",
              "Objetivos": "2",
              "Equipo": "MIA"
            },
            {
              "Fumbles": "",
              "Fumbles perdidos": "",
              "Intentos": "",
              "Comp": "",
              "INT": "",
              "Largo pase": "",
              "Rating": "",
              "Capturas recibidas": "",
              "Yds perdidas capturas": "",
              "TD pase": "",
              "Yds pase": "",
              "Nombre": "Rishard Matthews",
              "Rec": "1",
              "Largo recepción": "5",
              "TD recepción": "",
              "Yds recepción": "5",
              "Acarreos": "",
              "Largo carrera": "",
              "TD carrera": "",
              "Yds carrera": "",
              "Objetivos": "2",
              "Equipo": "MIA"
            },
            {
              "Fumbles": "1",
              "Fumbles perdidos": "",
              "Intentos": "",
              "Comp": "",
              "INT": "",
              "Largo pase": "",
              "Rating": "",
              "Capturas recibidas": "",
              "Yds perdidas capturas": "",
              "TD pase": "",
              "Yds pase": "",
              "Nombre": "Marcus Thigpen",
              "Rec": "1",
              "Largo recepción": "4",
              "TD recepción": "",
              "Yds recepción": "4",
              "Acarreos": "",
              "Largo carrera": "",
              "TD carrera": "",
              "Yds carrera": "",
              "Objetivos": "1",
              "Equipo": "MIA"
            }
          ]
        },
        "Puntos": 34,
        "Record": "7-6"
      },
      "Pittsburgh Steelers": {
        "Coach": "Mike Tomlin",
        "Estadísticas": {
          "Acarreos-yardas-TD": "21-84-0",
          "Capturas-yardas perdidas": "3-21",
          "Comp-Int-Yds-TD-INT": "23-39-349-3-0",
          "Conv. en cuarto down": "1-2",
          "Conv. en tercer down": "8-17",
          "Fumbles-perdidos": "1-1",
          "Penalizaciones-yardas": "9-63",
          "Primeros downs": "16",
          "Pérdidas de balón": "1",
          "Tiempo de posesión": "31:05",
          "Yardas netas por pase": "328",
          "Yardas totales": "412"
        },
        "Estadísticas por jugador": {
          "Defensiva": [
            {
              "INT": "1",
              "INT largo": "19",
              "TD INT": "1",
              "Yds INT": "19",
              "FF": "",
              "FR": "",
              "TD FR": "",
              "Yds FR": "",
              "Pases defendidos": "3",
              "Nombre": "Troy Polamalu",
              "Golpes QB": "",
              "Capturas": "",
              "Asist": "",
              "Tackles": "1",
              "TFL": "",
              "Solo": "1",
              "Equipo": "PIT"
            },
            {
              "INT": "",
              "INT largo": "",
              "TD INT": "",
              "Yds INT": "",
              "FF": "",
              "FR": "",
              "TD FR": "",
              "Yds FR": "",
              "Pases defendidos": "1",
              "Nombre": "Cameron Heyward",
              "Golpes QB": "1",
              "Capturas": "1",
              "Asist": "3",
              "Tackles": "10",
              "TFL": "1",
              "Solo": "7",
              "Equipo": "PIT"
            },
            {
              "INT": "",
              "INT largo": "",
              "TD INT": "",
              "Yds INT": "",
              "FF": "",
              "FR": "",
              "TD FR": "",
              "Yds FR": "",
              "Pases defendidos": "",
              "Nombre": "Jason Worilds",
              "Golpes QB": "3",
              "Capturas": "1",
              "Asist": "",
              "Tackles": "8",
              "TFL": "3",
              "Solo": "8",
              "Equipo": "PIT"
            },
            {
              "INT": "",
              "INT largo": "",
              "TD INT": "",
              "Yds INT": "",
              "FF": "",
              "FR": "",
              "TD FR": "",
              "Yds FR": "",
              "Pases defendidos": "",
              "Nombre": "William Gay",
              "Golpes QB": "",
              "Capturas": "",
              "Asist": "",
              "Tackles": "7",
              "TFL": "",
              "Solo": "7",
              "Equipo": "PIT"
            },
            {
              "INT": "",
              "INT largo": "",
              "TD INT": "",
              "Yds INT": "",
              "FF": "",
              "FR": "",
              "TD FR": "",
              "Yds FR": "",
              "Pases defendidos": "",
              "Nombre": "Ryan Clark",
              "Golpes QB": "",
              "Capturas": "",
              "Asist": "3",
              "Tackles": "5",
              "TFL": "",
              "Solo": "2",
              "Equipo": "PIT"
            },
            {
              "INT": "",
              "INT largo": "",
              "TD INT": "",
              "Yds INT": "",
              "FF": "",
              "FR": "",
              "TD FR": "",
              "Yds FR": "",
              "Pases defendidos": "",
              "Nombre": "Lawrence Timmons",
              "Golpes QB": "",
              "Capturas": "",
              "Asist": "1",
              "Tackles": "5",
              "TFL": "1",
              "Solo": "4",
              "Equipo": "PIT"
            },
            {
              "INT": "",
              "INT largo": "",
              "TD INT": "",
              "Yds INT": "",
              "FF": "",
              "FR": "",
              "TD FR": "",
              "Yds FR": "",
              "Pases defendidos": "",
              "Nombre": "Will Allen",
              "Golpes QB": "",
              "Capturas": "",
              "Asist": "2",
              "Tackles": "4",
              "TFL": "",
              "Solo": "2",
              "Equipo": "PIT"
            },
            {
              "INT": "",
              "INT largo": "",
              "TD INT": "",
              "Yds INT": "",
              "FF": "",
              "FR": "",
              "TD FR": "",
              "Yds FR": "",
              "Pases defendidos": "2",
              "Nombre": "Cortez Allen",
              "Golpes QB": "",
              "Capturas": "",
              "Asist": "",
              "Tackles": "3",
              "TFL": "",
              "Solo": "3",
              "Equipo": "PIT"
            },
            {
              "INT": "",
              "INT largo": "",
              "TD INT": "",
              "Yds INT": "",
              "FF": "",
              "FR": "",
              "TD FR": "",
              "Yds FR": "",
              "Pases defendidos": "",
              "Nombre": "Robert Golden",
              "Golpes QB": "",
              "Capturas": "",
              "Asist": "",
              "Tackles": "3",
              "TFL": "",
              "Solo": "3",
              "Equipo": "PIT"
            },
            {
              "INT": "",
              "INT largo": "",
              "TD INT": "",
              "Yds INT": "",
              "FF": "",
              "FR": "",
              "TD FR": "",
              "Yds FR": "",
              "Pases defendidos": "",
              "Nombre": "Evander Hood",
              "Golpes QB": "",
              "Capturas": "",
              "Asist": "",
              "Tackles": "3",
              "TFL": "",
              "Solo": "3",
              "Equipo": "PIT"
            },
            {
              "INT": "",
              "INT largo": "",
              "TD INT": "",
              "Yds INT": "",
              "FF": "",
              "FR": "",
              "TD FR": "",
              "Yds FR": "",
              "Pases defendidos": "",
              "Nombre": "Ike Taylor",
              "Golpes QB": "",
              "Capturas": "",
              "Asist": "1",
              "Tackles": "3",
              "TFL": "",
              "Solo": "2",
              "Equipo": "PIT"
            },
            {
              "INT": "",
              "INT largo": "",
              "TD INT": "",
              "Yds INT": "",
              "FF": "",
              "FR": "",
              "TD FR": "",
              "Yds FR": "",
              "Pases defendidos": "",
              "Nombre": "Vince Williams",
              "Golpes QB": "",
              "Capturas": "",
              "Asist": "3",
              "Tackles": "3",
              "TFL": "",
              "Solo": "",
              "Equipo": "PIT"
            },
            {
              "INT": "",
              "INT largo": "",
              "TD INT": "",
              "Yds INT": "",
              "FF": "",
              "FR": "",
              "TD FR": "",
              "Yds FR": "",
              "Pases defendidos": "",
              "Nombre": "LaMarr Woodley",
              "Golpes QB": "1",
              "Capturas": "",
              "Asist": "2",
              "Tackles": "3",
              "TFL": "",
              "Solo": "1",
              "Equipo": "PIT"
            },
            {
              "INT": "",
              "INT largo": "",
              "TD INT": "",
              "Yds INT": "",
              "FF": "",
              "FR": "",
              "TD FR": "",
              "Yds FR": "",
              "Pases defendidos": "",
              "Nombre": "Jarvis Jones",
              "Golpes QB": "",
              "Capturas": "",
              "Asist": "2",
              "Tackles": "2",
              "TFL": "",
              "Solo": "",
              "Equipo": "PIT"
            },
            {
              "INT": "",
              "INT largo": "",
              "TD INT": "",
              "Yds INT": "",
              "FF": "",
              "FR": "",
              "TD FR": "",
              "Yds FR": "",
              "Pases defendidos": "",
              "Nombre": "Terence Garvin",
              "Golpes QB": "",
              "Capturas": "",
              "Asist": "",
              "Tackles": "1",
              "TFL": "",
              "Solo": "1",
              "Equipo": "PIT"
            },
            {
              "INT": "",
              "INT largo": "",
              "TD INT": "",
              "Yds INT": "",
              "FF": "",
              "FR": "",
              "TD FR": "",
              "Yds FR": "",
              "Pases defendidos": "",
              "Nombre": "Will Johnson",
              "Golpes QB": "",
              "Capturas": "",
              "Asist": "",
              "Tackles": "1",
              "TFL": "",
              "Solo": "1",
              "Equipo": "PIT"
            },
            {
              "INT": "",
              "INT largo": "",
              "TD INT": "",
              "Yds INT": "",
              "FF": "",
              "FR": "",
              "TD FR": "",
              "Yds FR": "",
              "Pases defendidos": "",
              "Nombre": "Steve McLendon",
              "Golpes QB": "",
              "Capturas": "",
              "Asist": "1",
              "Tackles": "1",
              "TFL": "",
              "Solo": "",
              "Equipo": "PIT"
            },
            {
              "INT": "",
              "INT largo": "",
              "TD INT": "",
              "Yds INT": "",
              "FF": "1",
              "FR": "",
              "TD FR": "",
              "Yds FR": "",
              "Pases defendidos": "",
              "Nombre": "Shaun Suisham",
              "Golpes QB": "",
              "Capturas": "",
              "Asist": "",
              "Tackles": "1",
              "TFL": "",
              "Solo": "1",
              "Equipo": "PIT"
            },
            {
              "INT": "",
              "INT largo": "",
              "TD INT": "",
              "Yds INT": "",
              "FF": "",
              "FR": "",
              "TD FR": "",
              "Yds FR": "",
              "Pases defendidos": "",
              "Nombre": "Markus Wheaton",
              "Golpes QB": "",
              "Capturas": "",
              "Asist": "",
              "Tackles": "1",
              "TFL": "",
              "Solo": "1",
              "Equipo": "PIT"
            }
          ],
          "Equipos especiales": [
            {
              "FGa": "",
              "FGm": "",
              "Nombre": "Shaun Suisham",
              "Punts": "",
              "Largo punt": "",
              "Yds punt": "",
              "Prom punt": "",
              "Equipo": "PIT",
              "XPa": "4",
              "XPm": "4"
            },
            {
              "FGa": "",
              "FGm": "",
              "Nombre": "Mat McBriar",
              "Punts": "5",
              "Largo punt": "54",
              "Yds punt": "234",
              "Prom punt": "46.80",
              "Equipo": "PIT",
              "XPa": "",
              "XPm": ""
            },
            {
              "Retornos KO": "",
              "Largo retorno KO": "",
              "TD KO": "",
              "Yds KO": "",
              "Prom KO": "",
              "Nombre": "Antonio Brown",
              "Retornos punt": "5",
              "Largo retorno punt": "7",
              "TD punt": "",
              "Yds punt": "14",
              "Prom punt": "2.80",
              "Equipo": "PIT"
            },
            {
              "Retornos KO": "5",
              "Largo retorno KO": "26",
              "TD KO": "",
              "Yds KO": "103",
              "Prom KO": "20.60",
              "Nombre": "Emmanuel Sanders",
              "Retornos punt": "",
              "Largo retorno punt": "",
              "TD punt": "",
              "Yds punt": "",
              "Prom punt": "",
              "Equipo": "PIT"
            }
          ],
          "Ofensiva": [
            {
              "Fumbles": "1",
              "Fumbles perdidos": "1",
              "Intentos": "39",
              "Comp": "23",
              "INT": "",
              "Largo pase": "67",
              "Rating": "114.20",
              "Capturas recibidas": "3",
              "Yds perdidas capturas": "21",
              "TD pase": "3",
              "Yds pase": "349",
              "Nombre": "Ben Roethlisberger",
              "Rec": "",
              "Largo recepción": "5",
              "TD recepción": "",
              "Yds recepción": "5",
              "Acarreos": "1",
              "Largo carrera": "8",
              "TD carrera": "",
              "Yds carrera": "8",
              "Objetivos": "",
              "Equipo": "PIT"
            },
            {
              "Fumbles": "",
              "Fumbles perdidos": "",
              "Intentos": "",
              "Comp": "",
              "INT": "",
              "Largo pase": "",
              "Rating": "",
              "Capturas recibidas": "",
              "Yds perdidas capturas": "",
              "TD pase": "",
              "Yds pase": "",
              "Nombre": "Le'Veon Bell",
              "Rec": "5",
              "Largo recepción": "10",
              "TD recepción": "",
              "Yds recepción": "19",
              "Acarreos": "15",
              "Largo carrera": "9",
              "TD carrera": "",
              "Yds carrera": "61",
              "Objetivos": "9",
              "Equipo": "PIT"
            },
            {
              "Fumbles": "",
              "Fumbles perdidos": "",
              "Intentos": "",
              "Comp": "",
              "INT": "",
              "Largo pase": "",
              "Rating": "",
              "Capturas recibidas": "",
              "Yds perdidas capturas": "",
              "TD pase": "",
              "Yds pase": "",
              "Nombre": "Jonathan Dwyer",
              "Rec": "",
              "Largo recepción": "",
              "TD recepción": "",
              "Yds recepción": "",
              "Acarreos": "3",
              "Largo carrera": "6",
              "TD carrera": "",
              "Yds carrera": "8",
              "Objetivos": "",
              "Equipo": "PIT"
            },
            {
              "Fumbles": "",
              "Fumbles perdidos": "",
              "Intentos": "",
              "Comp": "",
              "INT": "",
              "Largo pase": "",
              "Rating": "",
              "Capturas recibidas": "",
              "Yds perdidas capturas": "",
              "TD pase": "",
              "Yds pase": "",
              "Nombre": "Felix Jones",
              "Rec": "",
              "Largo recepción": "",
              "TD recepción": "",
              "Yds recepción": "",
              "Acarreos": "2",
              "Largo carrera": "5",
              "TD carrera": "",
              "Yds carrera": "7",
              "Objetivos": "",
              "Equipo": "PIT"
            },
            {
              "Fumbles": "",
              "Fumbles perdidos": "",
              "Intentos": "",
              "Comp": "",
              "INT": "",
              "Largo pase": "",
              "Rating": "",
              "Capturas recibidas": "",
              "Yds perdidas capturas": "",
              "TD pase": "",
              "Yds pase": "",
              "Nombre": "Antonio Brown",
              "Rec": "5",
              "Largo recepción": "56",
              "TD recepción": "1",
              "Yds recepción": "138",
              "Acarreos": "",
              "Largo carrera": "",
              "TD carrera": "",
              "Yds carrera": "",
              "Objetivos": "10",
              "Equipo": "PIT"
            },
            {
              "Fumbles": "",
              "Fumbles perdidos": "",
              "Intentos": "",
              "Comp": "",
              "INT": "",
              "Largo pase": "",
              "Rating": "",
              "Capturas recibidas": "",
              "Yds perdidas capturas": "",
              "TD pase": "",
              "Yds pase": "",
              "Nombre": "Emmanuel Sanders",
              "Rec": "4",
              "Largo recepción": "21",
              "TD recepción": "1",
              "Yds recepción": "65",
              "Acarreos": "",
              "Largo carrera": "",
              "TD carrera": "",
              "Yds carrera": "",
              "Objetivos": "7",
              "Equipo": "PIT"
            },
            {
              "Fumbles": "",
              "Fumbles perdidos": "",
              "Intentos": "",
              "Comp": "",
              "INT": "",
              "Largo pase": "",
              "Rating": "",
              "Capturas recibidas": "",
              "Yds perdidas capturas": "",
              "TD pase": "",
              "Yds pase": "",
              "Nombre": "Jerricho Cotchery",
              "Rec": "5",
              "Largo recepción": "19",
              "TD recepción": "1",
              "Yds recepción": "57",
              "Acarreos": "",
              "Largo carrera": "",
              "TD carrera": "",
              "Yds carrera": "",
              "Objetivos": "9",
              "Equipo": "PIT"
            },
            {
              "Fumbles": "",
              "Fumbles perdidos": "",
              "Intentos": "",
              "Comp": "",
              "INT": "",
              "Largo pase": "",
              "Rating": "",
              "Capturas recibidas": "",
              "Yds perdidas capturas": "",
              "TD pase": "",
              "Yds pase": "",
              "Nombre": "Heath Miller",
              "Rec": "3",
              "Largo recepción": "31",
              "TD recepción": "",
              "Yds recepción": "56",
              "Acarreos": "",
              "Largo carrera": "",
              "TD carrera": "",
              "Yds carrera": "",
              "Objetivos": "4",
              "Equipo": "PIT"
            },
            {
              "Fumbles": "",
              "Fumbles perdidos": "",
              "Intentos": "",
              "Comp": "",
              "INT": "",
              "Largo pase": "",
              "Rating": "",
              "Capturas recibidas": "",
              "Yds perdidas capturas": "",
              "TD pase": "",
              "Yds pase": "",
              "Nombre": "Will Johnson",
              "Rec": "1",
              "Largo recepción": "9",
              "TD recepción": "",
              "Yds recepción": "9",
              "Acarreos": "",
              "Largo carrera": "",
              "TD carrera": "",
              "Yds carrera": "",
              "Objetivos": "1",
              "Equipo": "PIT"
            },
            {
              "Fumbles": "",
              "Fumbles perdidos": "",
              "Intentos": "",
              "Comp": "",
              "INT": "",
              "Largo pase": "",
              "Rating": "",
              "Capturas recibidas": "",
              "Yds perdidas capturas": "",
              "TD pase": "",
              "Yds pase": "",
              "Nombre": "Markus Wheaton",
              "Rec": "",
              "Largo recepción": "",
              "TD recepción": "",
              "Yds recepción": "",
              "Acarreos": "",
              "Largo carrera": "",
              "TD carrera": "",
              "Yds carrera": "",
              "Objetivos": "1",
              "Equipo": "PIT"
            }
          ]
        },
        "Puntos": 28,
        "Record": "5-8"
      }
    },
    "Estadísticas avanzadas": {
      "Puntos esperados": [
        {
          "PE Def. Pase": "-5.68",
          "PE Def. Carrera": "2.76",
          "PE Def. Pérdidas": "3.88",
          "PE Def. Total": "-2.11",
          "PE FG/XP": "-2.22",
          "PE Kicker": "1.64",
          "PE Ret. KO": "-1.80",
          "PE Of. Pase": "2.34",
          "PE Of. Carrera": "1.64",
          "PE Of. Pérdidas": "-6.07",
          "PE Of. Total": "3.65",
          "PE Punter": "3.50",
          "PE Ret. Punt": "0.54",
          "PE Equipos Esp.": "1.66",
          "PE Total": "6",
          "Equipo": "Dolphins"
        },
        {
          "PE Def. Pase": "-2.34",
          "PE Def. Carrera": "-1.64",
          "PE Def. Pérdidas": "6.07",
          "PE Def. Total": "-3.65",
          "PE FG/XP": "2.22",
          "PE Kicker": "1.80",
          "PE Ret. KO": "-1.64",
          "PE Of. Pase": "5.68",
          "PE Of. Carrera": "-2.76",
          "PE Of. Pérdidas": "-3.88",
          "PE Of. Total": "2.11",
          "PE Punter": "-0.54",
          "PE Ret. Punt": "-3.50",
          "PE Equipos Esp.": "-1.66",
          "PE Total": "-6",
          "Equipo": "Steelers"
        }
      ]
    },
    "Información del partido": {
      "Semana": "14",
      "Fecha": "8 de diciembre de 2013",
      "Estadio": "Heinz Field",
      "Tipo de estadio": "Al aire libre",
      "Superficie de juego": "Césped",
      "Clima": "25 grados, humedad relativa 73%, viento 9 mph, viento chill 16"
    },
    "Oficiales": [
      {
        "Nombre": "John Parry",
        "Posición": "Referee"
      },
      {
        "Nombre": "Dan Ferrell",
        "Posición": "Umpire"
      },
      {
        "Nombre": "Derick Bowers",
        "Posición": "Head Linesman"
      },
      {
        "Nombre": "Adrian Hill",
        "Posición": "Line Judge"
      },
      {
        "Nombre": "Perry Paganelli",
        "Posición": "Back Judge"
      },
      {
        "Nombre": "Joe Larrew",
        "Posición": "Side Judge"
      },
      {
        "Nombre": "Scott Edwards",
        "Posición": "Field Judge"
      }
    ],
    "Series ofensivas": {
      "Miami Dolphins": [
        {
          "#": "1",
          "Resultado": "Punt",
          "Yardas netas": "-6",
          "Jugadas": "3",
          "Cuarto": "1",
          "Posición cancha": "MIA 31",
          "Inicio": "12:52",
          "Tiempo": "1:27"
        },
        {
          "#": "2",
          "Resultado": "Field Goal",
          "Yardas netas": "64",
          "Jugadas": "8",
          "Cuarto": "1",
          "Posición cancha": "MIA 24",
          "Inicio": "4:20",
          "Tiempo": "3:40"
        },
        {
          "#": "3",
          "Resultado": "Punt",
          "Yardas netas": "3",
          "Jugadas": "5",
          "Cuarto": "2",
          "Posición cancha": "MIA 25",
          "Inicio": "14:43",
          "Tiempo": "2:25"
        },
        {
          "#": "4",
          "Resultado": "Touchdown",
          "Yardas netas": "31",
          "Jugadas": "5",
          "Cuarto": "2",
          "Posición cancha": "PIT 31",
          "Inicio": "10:44",
          "Tiempo": "2:29"
        },
        {
          "#": "5",
          "Resultado": "Punt",
          "Yardas netas": "-3",
          "Jugadas": "3",
          "Cuarto": "2",
          "Posición cancha": "MIA 24",
          "Inicio": "4:42",
          "Tiempo": "2:21"
        },
        {
          "#": "6",
          "Resultado": "Missed FG",
          "Yardas netas": "8",
          "Jugadas": "4",
          "Cuarto": "2",
          "Posición cancha": "PIT 42",
          "Inicio": "0:39",
          "Tiempo": "0:39"
        },
        {
          "#": "7",
          "Resultado": "Touchdown",
          "Yardas netas": "80",
          "Jugadas": "9",
          "Cuarto": "3",
          "Posición cancha": "MIA 20",
          "Inicio": "15:00",
          "Tiempo": "4:10"
        },
        {
          "#": "8",
          "Resultado": "Interception",
          "Yardas netas": "-2",
          "Jugadas": "2",
          "Cuarto": "3",
          "Posición cancha": "MIA 10",
          "Inicio": "8:58",
          "Tiempo": "0:53"
        },
        {
          "#": "9",
          "Resultado": "Touchdown",
          "Yardas netas": "71",
          "Jugadas": "7",
          "Cuarto": "3",
          "Posición cancha": "MIA 29",
          "Inicio": "8:05",
          "Tiempo": "3:13"
        },
        {
          "#": "10",
          "Resultado": "Punt",
          "Yardas netas": "13",
          "Jugadas": "6",
          "Cuarto": "4",
          "Posición cancha": "MIA 25",
          "Inicio": "14:56",
          "Tiempo": "3:01"
        },
        {
          "#": "11",
          "Resultado": "Punt",
          "Yardas netas": "3",
          "Jugadas": "3",
          "Cuarto": "4",
          "Posición cancha": "MIA 21",
          "Inicio": "9:35",
          "Tiempo": "1:44"
        },
        {
          "#": "12",
          "Resultado": "Touchdown",
          "Yardas netas": "80",
          "Jugadas": "4",
          "Cuarto": "4",
          "Posición cancha": "MIA 20",
          "Inicio": "4:31",
          "Tiempo": "1:38"
        },
        {
          "#": "13",
          "Resultado": "Field Goal",
          "Yardas netas": "",
          "Jugadas": "4",
          "Cuarto": "4",
          "Posición cancha": "PIT 9",
          "Inicio": "2:23",
          "Tiempo": "1:15"
        }
      ],
      "Pittsburgh Steelers": [
        {
          "#": "1",
          "Resultado": "Punt",
          "Yardas netas": "8",
          "Jugadas": "3",
          "Cuarto": "1",
          "Posición cancha": "PIT 20",
          "Inicio": "15:00",
          "Tiempo": "2:08"
        },
        {
          "#": "2",
          "Resultado": "Touchdown",
          "Yardas netas": "74",
          "Jugadas": "12",
          "Cuarto": "1",
          "Posición cancha": "PIT 26",
          "Inicio": "11:25",
          "Tiempo": "7:05"
        },
        {
          "#": "3",
          "Resultado": "Punt",
          "Yardas netas": "-1",
          "Jugadas": "3",
          "Cuarto": "1",
          "Posición cancha": "PIT 35",
          "Inicio": "0:40",
          "Tiempo": "0:57"
        },
        {
          "#": "4",
          "Resultado": "Fumble",
          "Yardas netas": "5",
          "Jugadas": "3",
          "Cuarto": "2",
          "Posición cancha": "PIT 26",
          "Inicio": "12:18",
          "Tiempo": "1:34"
        },
        {
          "#": "5",
          "Resultado": "Punt",
          "Yardas netas": "18",
          "Jugadas": "6",
          "Cuarto": "2",
          "Posición cancha": "PIT 20",
          "Inicio": "8:15",
          "Tiempo": "3:33"
        },
        {
          "#": "6",
          "Resultado": "Blocked Punt",
          "Yardas netas": "2",
          "Jugadas": "3",
          "Cuarto": "2",
          "Posición cancha": "PIT 40",
          "Inicio": "2:21",
          "Tiempo": "1:42"
        },
        {
          "#": "7",
          "Resultado": "Touchdown",
          "Yardas netas": "83",
          "Jugadas": "4",
          "Cuarto": "3",
          "Posición cancha": "PIT 17",
          "Inicio": "10:50",
          "Tiempo": "1:52"
        },
        {
          "#": "8",
          "Resultado": "Touchdown",
          "Yardas netas": "78",
          "Jugadas": "11",
          "Cuarto": "3",
          "Posición cancha": "PIT 22",
          "Inicio": "4:52",
          "Tiempo": "4:56"
        },
        {
          "#": "9",
          "Resultado": "Punt",
          "Yardas netas": "18",
          "Jugadas": "6",
          "Cuarto": "4",
          "Posición cancha": "PIT 17",
          "Inicio": "11:55",
          "Tiempo": "2:20"
        },
        {
          "#": "10",
          "Resultado": "Punt",
          "Yardas netas": "15",
          "Jugadas": "4",
          "Cuarto": "4",
          "Posición cancha": "PIT 37",
          "Inicio": "7:51",
          "Tiempo": "3:20"
        },
        {
          "#": "11",
          "Resultado": "Downs",
          "Yardas netas": "8",
          "Jugadas": "4",
          "Cuarto": "4",
          "Posición cancha": "PIT 10",
          "Inicio": "2:53",
          "Tiempo": "0:30"
        },
        {
          "#": "12",
          "Resultado": "End of Game",
          "Yardas netas": "68",
          "Jugadas": "4",
          "Cuarto": "4",
          "Posición cancha": "PIT 20",
          "Inicio": "1:08",
          "Tiempo": "1:08"
        }
      ]
    },
    "Videos del partido": []
  }
}