{
  "schema": {
    "name": "mundodolphins.hugo.sectioned-page",
    "version": "1.0.0"
  },
  "generated_at": "2026-02-18T11:41:05Z",
  "page": {
    "kind": "game",
    "title": "Miami Dolphins vs Indianapolis Colts",
    "date": "1986-10-26",
    "slug": "mia-ind-19861026",
    "path": "historia/partidos/mia-ind-19861026",
    "params": {
      "game_id": "198610260clt"
    }
  },
  "sections": {
    "Anotaciones": {
      "linescore": [
        {
          "Equipo": "Miami Dolphins",
          "1": "7",
          "2": "10",
          "3": "0",
          "4": "0",
          "Final": "17"
        },
        {
          "Equipo": "Indianapolis Colts",
          "1": "7",
          "2": "3",
          "3": "0",
          "4": "3",
          "Final": "13"
        }
      ],
      "scoring_summary": [
        {
          "Cuarto": "1",
          "Equipo": "Miami Dolphins",
          "Descripción": "Lorenzo Hampton carrera de 1 yarda (Fuad Reveiz kick)",
          "Marcador visitante": "7",
          "Marcador local": "0"
        },
        {
          "Cuarto": "1",
          "Equipo": "Indianapolis Colts",
          "Descripción": "Randy McMillan carrera de 14 yardas (Dean Biasucci kick)",
          "Marcador visitante": "7",
          "Marcador local": "7"
        },
        {
          "Cuarto": "2",
          "Equipo": "Miami Dolphins",
          "Descripción": "Fuad Reveiz field goal de 29 yardas",
          "Marcador visitante": "10",
          "Marcador local": "7"
        },
        {
          "Cuarto": "2",
          "Equipo": "Miami Dolphins",
          "Descripción": "Mark Duper pase de 7 yardas de Dan Marino (Fuad Reveiz kick)",
          "Marcador visitante": "17",
          "Marcador local": "7"
        },
        {
          "Cuarto": "2",
          "Equipo": "Indianapolis Colts",
          "Descripción": "Dean Biasucci field goal de 39 yardas",
          "Marcador visitante": "17",
          "Marcador local": "10"
        },
        {
          "Cuarto": "4",
          "Equipo": "Indianapolis Colts",
          "Descripción": "Dean Biasucci field goal de 45 yardas",
          "Marcador visitante": "17",
          "Marcador local": "13"
        }
      ]
    },
    "Conteo de snaps": {},
    "Equipos": {
      "Indianapolis Colts": {
        "Coach": "Rod Dowhower",
        "Estadísticas": {
          "Acarreos-yardas-TD": "36-182-1",
          "Capturas-yardas perdidas": "0-0",
          "Comp-Int-Yds-TD-INT": "14-24-121-0-1",
          "Fumbles-perdidos": "0-0",
          "Penalizaciones-yardas": "3-18",
          "Primeros downs": "17",
          "Pérdidas de balón": "1",
          "Tiempo de posesión": "27:48",
          "Yardas netas por pase": "121",
          "Yardas totales": "303"
        },
        "Estadísticas por jugador": {
          "Defensiva": [
            {
              "INT": "",
              "INT largo": "",
              "TD INT": "",
              "Yds INT": "",
              "FF": "1",
              "FR": "",
              "TD FR": "",
              "Yds FR": "",
              "Nombre": "Tate Randle",
              "Capturas": "",
              "Asist": "",
              "Tackles": "",
              "Solo": "",
              "Equipo": "IND"
            }
          ],
          "Equipos especiales": [
            {
              "FGa": "2",
              "FGm": "2",
              "Nombre": "Dean Biasucci",
              "Punts": "",
              "Largo punt": "",
              "Yds punt": "",
              "Prom punt": "",
              "Equipo": "IND",
              "XPa": "1",
              "XPm": "1"
            },
            {
              "FGa": "",
              "FGm": "",
              "Nombre": "Rohn Stark",
              "Punts": "3",
              "Largo punt": "",
              "Yds punt": "131",
              "Prom punt": "43.70",
              "Equipo": "IND",
              "XPa": "",
              "XPm": ""
            },
            {
              "Retornos KO": "4",
              "Largo retorno KO": "",
              "TD KO": "",
              "Yds KO": "72",
              "Prom KO": "18",
              "Nombre": "Robbie Martin",
              "Retornos punt": "1",
              "Largo retorno punt": "",
              "TD punt": "",
              "Yds punt": "6",
              "Prom punt": "6",
              "Equipo": "IND"
            }
          ],
          "Ofensiva": [
            {
              "Intentos": "24",
              "Comp": "14",
              "INT": "1",
              "Largo pase": "16",
              "Rating": "54.30",
              "Capturas recibidas": "",
              "Yds perdidas capturas": "",
              "TD pase": "",
              "Yds pase": "121",
              "Nombre": "Jack Trudeau",
              "Rec": "",
              "Largo recepción": "",
              "TD recepción": "",
              "Yds recepción": "",
              "Acarreos": "1",
              "Largo carrera": "4",
              "TD carrera": "",
              "Yds carrera": "4",
              "Objetivos": "",
              "Equipo": "IND"
            },
            {
              "Intentos": "",
              "Comp": "",
              "INT": "",
              "Largo pase": "",
              "Rating": "",
              "Capturas recibidas": "",
              "Yds perdidas capturas": "",
              "TD pase": "",
              "Yds pase": "",
              "Nombre": "George Wonsley",
              "Rec": "4",
              "Largo recepción": "10",
              "TD recepción": "",
              "Yds recepción": "34",
              "Acarreos": "18",
              "Largo carrera": "46",
              "TD carrera": "",
              "Yds carrera": "99",
              "Objetivos": "5",
              "Equipo": "IND"
            },
            {
              "Intentos": "",
              "Comp": "",
              "INT": "",
              "Largo pase": "",
              "Rating": "",
              "Capturas recibidas": "",
              "Yds perdidas capturas": "",
              "TD pase": "",
              "Yds pase": "",
              "Nombre": "Owen Gill",
              "Rec": "2",
              "Largo recepción": "11",
              "TD recepción": "",
              "Yds recepción": "19",
              "Acarreos": "12",
              "Largo carrera": "15",
              "TD carrera": "",
              "Yds carrera": "54",
              "Objetivos": "4",
              "Equipo": "IND"
            },
            {
              "Intentos": "",
              "Comp": "",
              "INT": "",
              "Largo pase": "",
              "Rating": "",
              "Capturas recibidas": "",
              "Yds perdidas capturas": "",
              "TD pase": "",
              "Yds pase": "",
              "Nombre": "Randy McMillan",
              "Rec": "1",
              "Largo recepción": "5",
              "TD recepción": "",
              "Yds recepción": "5",
              "Acarreos": "5",
              "Largo carrera": "14",
              "TD carrera": "1",
              "Yds carrera": "25",
              "Objetivos": "1",
              "Equipo": "IND"
            },
            {
              "Intentos": "",
              "Comp": "",
              "INT": "",
              "Largo pase": "",
              "Rating": "",
              "Capturas recibidas": "",
              "Yds perdidas capturas": "",
              "TD pase": "",
              "Yds pase": "",
              "Nombre": "Bill Brooks",
              "Rec": "2",
              "Largo recepción": "16",
              "TD recepción": "",
              "Yds recepción": "23",
              "Acarreos": "",
              "Largo carrera": "",
              "TD carrera": "",
              "Yds carrera": "",
              "Objetivos": "3",
              "Equipo": "IND"
            },
            {
              "Intentos": "",
              "Comp": "",
              "INT": "",
              "Largo pase": "",
              "Rating": "",
              "Capturas recibidas": "",
              "Yds perdidas capturas": "",
              "TD pase": "",
              "Yds pase": "",
              "Nombre": "Greg LaFleur",
              "Rec": "2",
              "Largo recepción": "11",
              "TD recepción": "",
              "Yds recepción": "21",
              "Acarreos": "",
              "Largo carrera": "",
              "TD carrera": "",
              "Yds carrera": "",
              "Objetivos": "2",
              "Equipo": "IND"
            },
            {
              "Intentos": "",
              "Comp": "",
              "INT": "",
              "Largo pase": "",
              "Rating": "",
              "Capturas recibidas": "",
              "Yds perdidas capturas": "",
              "TD pase": "",
              "Yds pase": "",
              "Nombre": "Matt Bouza",
              "Rec": "3",
              "Largo recepción": "7",
              "TD recepción": "",
              "Yds recepción": "19",
              "Acarreos": "",
              "Largo carrera": "",
              "TD carrera": "",
              "Yds carrera": "",
              "Objetivos": "6",
              "Equipo": "IND"
            },
            {
              "Intentos": "",
              "Comp": "",
              "INT": "",
              "Largo pase": "",
              "Rating": "",
              "Capturas recibidas": "",
              "Yds perdidas capturas": "",
              "TD pase": "",
              "Yds pase": "",
              "Nombre": "Walter Murray",
              "Rec": "",
              "Largo recepción": "",
              "TD recepción": "",
              "Yds recepción": "",
              "Acarreos": "",
              "Largo carrera": "",
              "TD carrera": "",
              "Yds carrera": "",
              "Objetivos": "3",
              "Equipo": "IND"
            }
          ]
        },
        "Puntos": 13,
        "Record": "0-8"
      },
      "Miami Dolphins": {
        "Coach": "Don Shula",
        "Estadísticas": {
          "Acarreos-yardas-TD": "29-97-1",
          "Capturas-yardas perdidas": "0-0",
          "Comp-Int-Yds-TD-INT": "23-42-243-1-0",
          "Fumbles-perdidos": "3-0",
          "Penalizaciones-yardas": "3-30",
          "Primeros downs": "21",
          "Pérdidas de balón": "",
          "Tiempo de posesión": "32:12",
          "Yardas netas por pase": "243",
          "Yardas totales": "340"
        },
        "Estadísticas por jugador": {
          "Defensiva": [
            {
              "INT": "1",
              "INT largo": "",
              "TD INT": "",
              "Yds INT": "",
              "FF": "",
              "FR": "",
              "TD FR": "",
              "Yds FR": "",
              "Nombre": "William Judson",
              "Capturas": "",
              "Asist": "",
              "Tackles": "",
              "Solo": "",
              "Equipo": "MIA"
            },
            {
              "INT": "",
              "INT largo": "",
              "TD INT": "",
              "Yds INT": "",
              "FF": "",
              "FR": "1",
              "TD FR": "",
              "Yds FR": "",
              "Nombre": "Dan Marino",
              "Capturas": "",
              "Asist": "",
              "Tackles": "",
              "Solo": "",
              "Equipo": "MIA"
            }
          ],
          "Equipos especiales": [
            {
              "FGa": "2",
              "FGm": "1",
              "Nombre": "Fuad Reveiz",
              "Punts": "",
              "Largo punt": "",
              "Yds punt": "",
              "Prom punt": "",
              "Equipo": "MIA",
              "XPa": "2",
              "XPm": "2"
            },
            {
              "FGa": "",
              "FGm": "",
              "Nombre": "Reggie Roby",
              "Punts": "3",
              "Largo punt": "",
              "Yds punt": "145",
              "Prom punt": "48.30",
              "Equipo": "MIA",
              "XPa": "",
              "XPm": ""
            },
            {
              "Retornos KO": "2",
              "Largo retorno KO": "",
              "TD KO": "",
              "Yds KO": "56",
              "Prom KO": "28",
              "Nombre": "Craig Ellis",
              "Retornos punt": "2",
              "Largo retorno punt": "",
              "TD punt": "",
              "Yds punt": "11",
              "Prom punt": "5.50",
              "Equipo": "MIA"
            },
            {
              "Retornos KO": "1",
              "Largo retorno KO": "",
              "TD KO": "",
              "Yds KO": "15",
              "Prom KO": "15",
              "Nombre": "Ron Davenport",
              "Retornos punt": "",
              "Largo retorno punt": "",
              "TD punt": "",
              "Yds punt": "",
              "Prom punt": "",
              "Equipo": "MIA"
            }
          ],
          "Ofensiva": [
            {
              "Intentos": "42",
              "Comp": "23",
              "INT": "",
              "Largo pase": "27",
              "Rating": "79.80",
              "Capturas recibidas": "",
              "Yds perdidas capturas": "",
              "TD pase": "1",
              "Yds pase": "243",
              "Nombre": "Dan Marino",
              "Rec": "",
              "Largo recepción": "",
              "TD recepción": "",
              "Yds recepción": "",
              "Acarreos": "4",
              "Largo carrera": "",
              "TD carrera": "",
              "Yds carrera": "-8",
              "Objetivos": "",
              "Equipo": "MIA"
            },
            {
              "Intentos": "",
              "Comp": "",
              "INT": "",
              "Largo pase": "",
              "Rating": "",
              "Capturas recibidas": "",
              "Yds perdidas capturas": "",
              "TD pase": "",
              "Yds pase": "",
              "Nombre": "Jim Jensen",
              "Rec": "",
              "Largo recepción": "",
              "TD recepción": "",
              "Yds recepción": "",
              "Acarreos": "",
              "Largo carrera": "",
              "TD carrera": "",
              "Yds carrera": "",
              "Objetivos": "1",
              "Equipo": "MIA"
            },
            {
              "Intentos": "",
              "Comp": "",
              "INT": "",
              "Largo pase": "",
              "Rating": "",
              "Capturas recibidas": "",
              "Yds perdidas capturas": "",
              "TD pase": "",
              "Yds pase": "",
              "Nombre": "Lorenzo Hampton",
              "Rec": "4",
              "Largo recepción": "16",
              "TD recepción": "",
              "Yds recepción": "47",
              "Acarreos": "13",
              "Largo carrera": "19",
              "TD carrera": "1",
              "Yds carrera": "58",
              "Objetivos": "7",
              "Equipo": "MIA"
            },
            {
              "Intentos": "",
              "Comp": "",
              "INT": "",
              "Largo pase": "",
              "Rating": "",
              "Capturas recibidas": "",
              "Yds perdidas capturas": "",
              "TD pase": "",
              "Yds pase": "",
              "Nombre": "Woody Bennett",
              "Rec": "",
              "Largo recepción": "",
              "TD recepción": "",
              "Yds recepción": "",
              "Acarreos": "5",
              "Largo carrera": "8",
              "TD carrera": "",
              "Yds carrera": "28",
              "Objetivos": "",
              "Equipo": "MIA"
            },
            {
              "Intentos": "",
              "Comp": "",
              "INT": "",
              "Largo pase": "",
              "Rating": "",
              "Capturas recibidas": "",
              "Yds perdidas capturas": "",
              "TD pase": "",
              "Yds pase": "",
              "Nombre": "Ron Davenport",
              "Rec": "3",
              "Largo recepción": "27",
              "TD recepción": "",
              "Yds recepción": "45",
              "Acarreos": "6",
              "Largo carrera": "6",
              "TD carrera": "",
              "Yds carrera": "19",
              "Objetivos": "3",
              "Equipo": "MIA"
            },
            {
              "Intentos": "",
              "Comp": "",
              "INT": "",
              "Largo pase": "",
              "Rating": "",
              "Capturas recibidas": "",
              "Yds perdidas capturas": "",
              "TD pase": "",
              "Yds pase": "",
              "Nombre": "James Pruitt",
              "Rec": "3",
              "Largo recepción": "18",
              "TD recepción": "",
              "Yds recepción": "35",
              "Acarreos": "",
              "Largo carrera": "",
              "TD carrera": "",
              "Yds carrera": "",
              "Objetivos": "3",
              "Equipo": "MIA"
            },
            {
              "Intentos": "",
              "Comp": "",
              "INT": "",
              "Largo pase": "",
              "Rating": "",
              "Capturas recibidas": "",
              "Yds perdidas capturas": "",
              "TD pase": "",
              "Yds pase": "",
              "Nombre": "Nat Moore",
              "Rec": "3",
              "Largo recepción": "24",
              "TD recepción": "",
              "Yds recepción": "34",
              "Acarreos": "",
              "Largo carrera": "",
              "TD carrera": "",
              "Yds carrera": "",
              "Objetivos": "4",
              "Equipo": "MIA"
            },
            {
              "Intentos": "",
              "Comp": "",
              "INT": "",
              "Largo pase": "",
              "Rating": "",
              "Capturas recibidas": "",
              "Yds perdidas capturas": "",
              "TD pase": "",
              "Yds pase": "",
              "Nombre": "Mark Clayton",
              "Rec": "2",
              "Largo recepción": "18",
              "TD recepción": "",
              "Yds recepción": "29",
              "Acarreos": "",
              "Largo carrera": "",
              "TD carrera": "",
              "Yds carrera": "",
              "Objetivos": "8",
              "Equipo": "MIA"
            },
            {
              "Intentos": "",
              "Comp": "",
              "INT": "",
              "Largo pase": "",
              "Rating": "",
              "Capturas recibidas": "",
              "Yds perdidas capturas": "",
              "TD pase": "",
              "Yds pase": "",
              "Nombre": "Tony Nathan",
              "Rec": "3",
              "Largo recepción": "16",
              "TD recepción": "",
              "Yds recepción": "28",
              "Acarreos": "",
              "Largo carrera": "",
              "TD carrera": "",
              "Yds carrera": "",
              "Objetivos": "3",
              "Equipo": "MIA"
            },
            {
              "Intentos": "",
              "Comp": "",
              "INT": "",
              "Largo pase": "",
              "Rating": "",
              "Capturas recibidas": "",
              "Yds perdidas capturas": "",
              "TD pase": "",
              "Yds pase": "",
              "Nombre": "Mark Duper",
              "Rec": "2",
              "Largo recepción": "7",
              "TD recepción": "1",
              "Yds recepción": "13",
              "Acarreos": "",
              "Largo carrera": "",
              "TD carrera": "",
              "Yds carrera": "",
              "Objetivos": "6",
              "Equipo": "MIA"
            },
            {
              "Intentos": "",
              "Comp": "",
              "INT": "",
              "Largo pase": "",
              "Rating": "",
              "Capturas recibidas": "",
              "Yds perdidas capturas": "",
              "TD pase": "",
              "Yds pase": "",
              "Nombre": "Bruce Hardy",
              "Rec": "3",
              "Largo recepción": "7",
              "TD recepción": "",
              "Yds recepción": "12",
              "Acarreos": "",
              "Largo carrera": "",
              "TD carrera": "",
              "Yds carrera": "",
              "Objetivos": "7",
              "Equipo": "MIA"
            },
            {
              "Intentos": "",
              "Comp": "",
              "INT": "",
              "Largo pase": "",
              "Rating": "",
              "Capturas recibidas": "",
              "Yds perdidas capturas": "",
              "TD pase": "",
              "Yds pase": "",
              "Nombre": "Reggie Roby",
              "Rec": "",
              "Largo recepción": "",
              "TD recepción": "",
              "Yds recepción": "",
              "Acarreos": "1",
              "Largo carrera": "",
              "TD carrera": "",
              "Yds carrera": "",
              "Objetivos": "",
              "Equipo": "MIA"
            }
          ]
        },
        "Puntos": 17,
        "Record": "3-5"
      }
    },
    "Estadísticas avanzadas": {
      "Puntos esperados": [
        {
          "PE Def. Pase": "-9.47",
          "PE Def. Carrera": "0.35",
          "PE Def. Pérdidas": "",
          "PE Def. Total": "-9.50",
          "PE FG/XP": "4.29",
          "PE Kicker": "0.78",
          "PE Ret. KO": "-3.03",
          "PE Of. Pase": "-3.14",
          "PE Of. Carrera": "-3.48",
          "PE Of. Pérdidas": "-3.92",
          "PE Of. Total": "2.33",
          "PE Punter": "1.40",
          "PE Ret. Punt": "1.85",
          "PE Equipos Esp.": "5.29",
          "PE Total": "-4",
          "Equipo": "Colts"
        },
        {
          "PE Def. Pase": "3.14",
          "PE Def. Carrera": "3.48",
          "PE Def. Pérdidas": "3.92",
          "PE Def. Total": "-2.33",
          "PE FG/XP": "-4.29",
          "PE Kicker": "3.03",
          "PE Ret. KO": "-0.78",
          "PE Of. Pase": "9.47",
          "PE Of. Carrera": "-0.35",
          "PE Of. Pérdidas": "",
          "PE Of. Total": "9.50",
          "PE Punter": "-1.85",
          "PE Ret. Punt": "-1.40",
          "PE Equipos Esp.": "-5.29",
          "PE Total": "4",
          "Equipo": "Dolphins"
        }
      ]
    },
    "Información del partido": {
      "Semana": "8",
      "Fecha": "26 de octubre de 1986",
      "Estadio": "Hoosier Dome",
      "Tipo de estadio": "dome",
      "Superficie de juego": "astroturf"
    },
    "Oficiales": [],
    "Series ofensivas": {},
    "Videos del partido": [
      {
        "youtube_id": "PWRPFfjO7go",
        "title": "Legacy import",
        "url": "https://www.youtube.com/watch?v=PWRPFfjO7go",
        "duration_seconds": 7940
      }
    ]
  }
}